[
{"出表日期":"1150122","發言日期":"1150121","發言時間":"70003","公司代號":"7780","公司名稱":"大研生醫*","主旨 ":"公告本公司股票面額由「新台幣10元」變更為「新台幣1元」，\r\n公告期間：114年12月22日至115年3月21日。","符合條款":"第51款","事實發生日":"1141127","說明":"1.事實發生日：民國114年11月27日\r\n2.公司名稱：大研生醫國際股份有限公司\r\n3.與公司關係(請輸入本公司或子公司)：本公司\r\n4.相互持股比例：不適用\r\n5.發生緣由：\r\n(1)公司面額變更核准日期/事實發生日：民國114年11月27日\r\n(2)公司面額變更核准文號：經授商字第臺證上一字第1140022289號號函\r\n(3)董事會決議通過換股計畫書日期：民國114年12月22日\r\n(4)變更前面額：新台幣10.00\r\n(5)變更後面額：新台幣1.00\r\n(6)新股票上市買賣日及舊股票終止上市買賣日：民國115年01月19日\r\n(7)換發股票時程重大訊息公告日期：民國114年12月22日重大訊息公告\r\n6.因應措施：無\r\n7.其他應敘明事項：一、換發股票時程如下：\r\n     (1)舊股票最後交易日:民國115年1月8日\r\n     (2)舊股票停止交易期間:民國115年1月9日至115年1月17日\r\n     (3)舊股票最後過戶日:民國115年1月12日\r\n     (4)舊股票停止過戶起始日期:民國115年1月13日\r\n     (5)舊股票停止過戶截止日期:民國115年1月17日\r\n     (6)換發股票基準日:民國115年1月17日\r\n     (7)有價證券換發日:民國115年1月19日\r\n     (8)新股票上市買賣日:民國115年1月19日\r\n     (9)舊股票終止上市買賣日:民國115年1月19日\r\n     (10)自新股票上市買賣之日起原上市買賣之舊股票不得作為買賣交割之標的，\r\n         本次換發新股票(採無實體方式)其權利義務與舊股票相同。\r\n二、本公司係辦理變更股票面額，每股面額由新台幣10元變更為新台幣1元，\r\n    業經臺灣證券交易所臺證上一字第1140022289號核准在案。\r\n三、配合上述面額變更，新股票上市買賣日之參考價將按比例調整\r\n    為舊股票最後交易日收盤價之十分之一，請投資人注意。\r\n四、股票面額變更後，財務資料(例如:每股盈餘或每股淨值等)將有所變動，\r\n    建議投資人可利用公開資訊觀測站公布之財務報告及財務比率分析等\r\n    作為投資分析指標參考。"},
{"出表日期":"1150122","發言日期":"1150121","發言時間":"94115","公司代號":"4526","公司名稱":"東台","主旨 ":"115年01月21日經濟日報報導澄清","符合條款":"第51款","事實發生日":"1150121","說明":"1.事實發生日:115/01/21\n2.公司名稱:東台精機股份有限公司\n3.與公司關係(請輸入本公司或子公司):本公司\n4.相互持股比例:不適用\n5.傳播媒體名稱:經濟日報\n6.報導內容:\n東台搶PCB鑽孔機商機 大陸吳江廠3月試量產 規劃月產能30台 全年拚續增雙位數\n7.發生緣由:大眾傳播媒體報導\n8.因應措施:本公司未提供財務預測，報載皆係媒體臆測，實際財務數字依公告為準。\n9.其他應敘明事項:無"},
{"出表日期":"1150122","發言日期":"1150121","發言時間":"94340","公司代號":"3550","公司名稱":"聯穎","主旨 ":"公告本公司及子公司對聯穎科技(安福)有限公司\r\n背書保證達公開發行公司資金貸與及背書保證處理\r\n準則第二十五條第一項第二、三及四款標準","符合條款":"第22款","事實發生日":"1150121","說明":"1.事實發生日:115/01/21\r\n2.被背書保證之:\r\n(1)公司名稱:聯穎科技(安福)有限公司\r\n(2)與提供背書保證公司之關係:\r\n同為本公司直接及間接持有表決權100%公司。\r\n(3)背書保證之限額(仟元):581,251\r\n(4)原背書保證之餘額(仟元):195,589\r\n(5)本次新增背書保證之金額(仟元):192,377\r\n(6)迄事實發生日止背書保證餘額(仟元):387,966\r\n(7)被背書保證公司實際動支金額(仟元):122,060\r\n(8)本次新增背書保證之原因:\r\n因應子公司營運需求,為其背書保證做為銀行借款之擔保\r\n原保證額度到期續約\r\n3.被背書保證公司提供擔保品之:\r\n(1)內容:\r\n無\r\n(2)價值(仟元):0\r\n4.被背書保證公司最近期財務報表之:\r\n(1)資本(仟元):173,472\r\n(2)累積盈虧金額(仟元):-140,615\r\n5.解除背書保證責任之:\r\n(1)條件:\r\n銀行授信條件變更或到期不再續約\r\n(2)日期:\r\n契約到期日或本息全數清償之日\r\n6.背書保證之總限額(仟元):\r\n1,835,463\r\n7.迄事實發生日為止，背書保證餘額(仟元):\r\n387,966\r\n8.迄事實發生日為止，A提供背書保證餘額占公開發行公司最近期財務報表淨值之\r\n比率:\r\n31.71\r\n9.迄事實發生日為止，背書保證、長期投資及資金貸與餘額合計數達該公開發行公\r\n司最近期財務報表淨值之比率:\r\n71.78\r\n10.其他應敘明事項:\r\n董事會通過，造成背書保證金額與現有背書保證金額重複。"},
{"出表日期":"1150122","發言日期":"1150121","發言時間":"100747","公司代號":"8261","公司名稱":"富鼎","主旨 ":"應主管機關要求，發布重大訊息，澄清媒體報導","符合條款":"第51款","事實發生日":"1150121","說明":"1.事實發生日:115/01/21\n2.公司名稱:富鼎先進電子股份有限公司\n3.與公司關係(請輸入本公司或子公司):本公司\n4.相互持股比例:不適用\n5.傳播媒體名稱:經濟日報\n6.報導內容:法人預期富鼎今年營收可望挑戰雙位數成長。\n7.發生緣由:報導的數據為媒體表達的內容，實際狀況\n應以本公司揭露於公開資訊觀測站之資訊為準，特此公告。\n8.因應措施:發布重大訊息，澄清媒體報導。\n9.其他應敘明事項:無"},
{"出表日期":"1150122","發言日期":"1150121","發言時間":"105829","公司代號":"5534","公司名稱":"長虹","主旨 ":"補正公告本公司訂定114年度現金增資認股基準日\r\n相關事宜","符合條款":"第11款","事實發生日":"1150121","說明":"1.董事會決議或公司決定增資基準日期:115/01/20\n2.是否採總括申報發行新股(是，請併敘明預定發行期間/否):否\n3.主管機關申報生效日期:115/01/14\n4.董事會決議(追補)發行日期:114/11/11及114/12/16\n5.發行總金額及股數:新臺幣250,000仟元；普通股25,000仟股\n6.採總括申報發行新股案件，本次發行金額及股數:NA\n7.採總括申報發行新股案件，本次發行後，剩餘之金額及股數餘額:NA\n8.每股面額:新臺幣10元\n9.發行價格:實際發行價格於訂定後另行公告。\n10.員工認股股數:依公司法267條規定，保留增資發行新股總額15%計3,750,000股，\n由本公司員工認購。\n11.原股東認購比率:增資發行新股之75%，計18,750,000股，由原股東按增資認股\n基準日股東名簿記載之股東持股比例認購。\n12.公開銷售方式及股數:依證券交易法第28條之1規定，提撥增資發行股數之10%\n計2,500,000股對外公開承銷。\n13.畸零股及逾期未認購股份之處理方式:認購不足一股之畸零股，由股東自停止\n過戶日前五日起至停止過戶日前一日止，逕向本公司股務辦事處辦理拼湊成整股\n認購。原股東及員工放棄認購或拼湊不足一股之畸零股，授權董事長洽特定人按\n發行價格認購之。\n14.本次發行新股之權利義務:與原有發行之普通股相同。\n15.本次增資資金用途:償還銀行借款。\n16.現金增資認股基準日:115/02/11\n17.最後過戶日:115/02/06\n18.停止過戶起始日期:115/02/07\n19.停止過戶截止日期:115/02/11\n20.股款繳納期間:\n原股東及員工股款繳納期間：115/02/13~115/03/16\n特定人繳款期間：115/03/17~115/03/19\n21.與代收及專戶存儲價款行庫訂約日期:俟正式簽約後另行公告。\n22.委託代收存款機構:俟正式簽約後另行公告。\n23.委託存儲款項機構:俟正式簽約後另行公告。\n24.其他應敘明事項:\n(1)上述日程如經主管機關指示，相關法令規則修正，或因應客觀環境需變更或\n修正時， 授權董事長視實際情況依相關法令規定辦理。\n(2)本次現金增資發行新股業經金管會115年1月14日金管證發字第1140369062號函\n申報生效在案。\n(3)參與現增之最後買進日：115/02/04"},
{"出表日期":"1150122","發言日期":"1150121","發言時間":"110538","公司代號":"1623","公司名稱":"大東電","主旨 ":"本公司股票即將終止興櫃交易並轉至臺灣證券交易所上市\r\n交易","符合條款":"第28款","事實發生日":"1150121","說明":"1.事實發生日:115/01/21\n2.停止或終止有價證券登錄興櫃股票之原因:轉至臺灣證券交易所上市交易\n3.預計或實際停止或終止有價證券登錄興櫃股票之日期:115/01/22\n4.其它應敘明事項:\n(1)本公司申請股票初次上市案，業經臺灣證券交易所股份有限公司114年11月27日\n   臺證上一字第1141805068號函核准上市。\n(2)本公司為配合初次上市前公開承銷辦理現金增資新台幣60,000,000元，發行普通\n   股6,000,000股，每股面額新台幣10元，業經臺灣證券交易所股份有限公司114年\n   12月15日臺證上一字第1140023280號函申報生效在案。\n(3)本公司向臺灣證券交易所股份有限公司洽定上市買賣開始日為115年01月22日，\n   並自同日起終止興櫃買賣。"},
{"出表日期":"1150122","發言日期":"1150121","發言時間":"112304","公司代號":"6177","公司名稱":"達麗","主旨 ":"澄清工商時報B4版報導","符合條款":"第51款","事實發生日":"1150121","說明":"1.事實發生日:115/01/21\n2.公司名稱:達麗建設事業股份有限公司\n3.與公司關係(請輸入本公司或子公司):本公司\n4.相互持股比例:不適用\n5.傳播媒體名稱:工商時報\n6.報導內容:達麗建設2026年推案腳步轉趨積極…市場樂觀全年營收將勝過2025年的\n95.31億元。達麗董事長謝志長對2026年房市頗有期待…。\n7.發生緣由:對於媒體報導內容發布重大訊息澄清\n8.因應措施:該營收數字係媒體及法人自行推估或解讀，本公司未對獲利做任何預估及\n財務預測，所有財務資訊悉依規定於公開資訊觀測站公布，特此說明。\n9.其他應敘明事項:無"},
{"出表日期":"1150122","發言日期":"1150121","發言時間":"133322","公司代號":"2634","公司名稱":"漢翔","主旨 ":"公告本公司發言人異動","符合條款":"第8款","事實發生日":"1150121","說明":"1.人員變動別（請輸入發言人、代理發言人、重要營運主管(如:執行長、營運長、\n行銷長及策略長等)、財務主管、會計主管、公司治理主管、資訊安全長、研發主管、\n內部稽核主管或訴訟及非訟代理人）:發言人\n2.發生變動日期:115/01/21\n3.舊任者姓名、級職及簡歷:無\n4.新任者姓名、級職及簡歷:莊秀美，漢翔航空工業股份有限公司總經理\n5.異動情形（請輸入「辭職」、「職務調整」、「資遣」、「退休」、「死亡」、「新\n任」或「解任」）:新任\n6.異動原因:新任\n7.生效日期:115/01/21\n8.其他應敘明事項:無"},
{"出表日期":"1150122","發言日期":"1150121","發言時間":"134535","公司代號":"3443","公司名稱":"創意","主旨 ":"本公司將於115/01/29召開董事會通過114年第四季財務報告","符合條款":"第31款","事實發生日":"1150121","說明":"1.董事會召集通知日:115/01/21\n2.董事會預計召開日期:115/01/29\n3.預計提報董事會或經董事會決議之財務報告或\n年度自結財務資訊年季:114年第四季\n4.其他應敘明事項:無"},
{"出表日期":"1150122","發言日期":"1150121","發言時間":"141739","公司代號":"3518","公司名稱":"柏騰","主旨 ":"公告本公司及子公司達公開發行公司資金貸與及背書保證\r\n處理準則第二十二條第一項第二款及第三款","符合條款":"第23款","事實發生日":"1150121","說明":"1.事實發生日:115/01/21\r\n2.接受資金貸與之:\r\n(1)公司名稱:晶成材料股份有限公司\r\n(2)與資金貸與他人公司之關係:\r\n本公司直接出資或透過持有表決權股份百分之百公司間\r\n(3)資金貸與之限額(仟元):430,513\r\n(4)原資金貸與之餘額(仟元):138,402\r\n(5)本次新增資金貸與之金額(仟元):54,360\r\n(6)是否為董事會授權董事長對同一貸與對象分次撥貸或循環動用之資金貸與:否\r\n(7)迄事實發生日止資金貸與餘額(仟元):192,762\r\n(8)本次新增資金貸與之原因:\r\n營運週轉需求\r\n3.接受資金貸與公司所提供擔保品之:\r\n(1)內容:\r\n無\r\n(2)價值(仟元):0\r\n4.接受資金貸與公司最近期財務報表之:\r\n(1)資本(仟元):780,000\r\n(2)累積盈虧金額(仟元):-247,244\r\n5.計息方式:\r\n年息0%\r\n6.還款之:\r\n(1)條件:\r\n到期償還本金\r\n(2)日期:\r\n借款後1年還款\r\n7.迄事實發生日為止，資金貸與餘額(仟元):\r\n256,182\r\n8.迄事實發生日為止，資金貸與餘額占公開發行公司最近期財務報表淨值之比率:\r\n19.33\r\n9.公司貸與他人資金之來源:\r\n子公司本身\r\n10.其他應敘明事項:\r\n無"},
{"出表日期":"1150122","發言日期":"1150121","發言時間":"142152","公司代號":"8467","公司名稱":"波力-KY","主旨 ":"本公司修訂「中華民國境內第二次有擔保轉換公司債發行\r\n及轉換辦法」及「中華民國境內第三次無擔保轉換公司債發行\r\n及轉換辦法」之債權人公告","符合條款":"第51款","事實發生日":"1150121","說明":"1.事實發生日:115/01/21\n2.公司名稱:波力環球企業股份有限公司\n3.與公司關係(請輸入本公司或子公司):本公司\n4.相互持股比例:不適用\n5.發生緣由:\n(1)依據金融監督管理委員會114年5月5日金管證發字第1140382105號函規定辦理。\n(2)本公司業經民國114年12月15日董事會決議通過修訂「中華民國境內第二次有擔保\n轉換公司債發行及轉換辦法」及「中華民國境內第三次無擔保轉換公司債發行及轉換\n辦法」並依法辦理債權人公告，至公告期間屆滿後，按公司法第248條第4項規定，呈\n奉證券主管機關申報核准。\n(3)本公司中華民國境內第二次有擔保轉換公司債及第三次無擔保轉換公司債債券持有\n人對於本次修訂「中華民國境內第二次有擔保轉換公司債發行及轉換辦法」及「中華民\n國境內第三次無擔保轉換公司債發行及轉換辦法」，如有異議者，請自本公告日起至\n115年2月23日之期限內，檢附相關債權證明文件，以書面方式掛號郵寄(郵寄以郵戳為\n憑)，向本公司提出，以便依法處理，受理處所為波力環球企業股份有限公司總經理室\n(地址：台中市潭子區民生街64巷15號)，逾期未表示即視為無異議，特此公告。\n6.因應措施:無\n7.其他應敘明事項(若事件發生或決議之主體係屬公開發行以上公司，本則重大訊息同時\n  符合證券交易法施行細則第7條第9款所定對股東權益或證券價格有重大影響之事項):\n本次修訂「中華民國境內第二次有擔保轉換公司債發行及轉換辦法」及「中華民國境內\n第三次無擔保轉換公司債發行及轉換辦法」部分條文相關事項，若因事實需要、法令規\n定或經主管機關審核要求而需修正或調整時，授權董事長全權處理。"},
{"出表日期":"1150122","發言日期":"1150121","發言時間":"143144","公司代號":"2455","公司名稱":"全新","主旨 ":"公告本公司國內第二次無擔保轉換公司債收足債款","符合條款":"第51款","事實發生日":"1150121","說明":"1.事實發生日:115/01/21\n2.公司名稱:全新光電科技股份有限公司\n3.與公司關係(請輸入本公司或子公司):本公司\n4.相互持股比例:不適用\n5.發生緣由:依據「發行人募集與發行有價證券處理準則」第九條第一項第二款規定辦理\n公告，本公司發行國內第二次無擔保轉換公司債至公告日止，債款代收銀行已收足所有\n應募款項共計新臺幣501,000,000元整，並匯撥至存儲專戶銀行，特此公告\n6.因應措施:不適用\n7.其他應敘明事項(若事件發生或決議之主體係屬公開發行以上公司，本則重大訊息同時\n  符合證券交易法施行細則第7條第9款所定對股東權益或證券價格有重大影響之事項):無"},
{"出表日期":"1150122","發言日期":"1150121","發言時間":"143837","公司代號":"7780","公司名稱":"大研生醫*","主旨 ":"公告本公司現金增資子公司Daiken Biomedical Australia Pty Ltd","符合條款":"第20款","事實發生日":"1150121","說明":"1.標的物之名稱及性質（屬特別股者，並應標明特別股約定發行條件，如股息率等）:\r\nDaiken Biomedical Australia Pty Ltd 股權\r\n2.事實發生日:115/1/21~115/1/21\r\n3.董事會通過日期: 民國115年1月21日\r\n4.其他核決日期: 不適用\r\n5.交易數量、每單位價格及交易總金額:\r\n(1)交易單位數量：增加60,000,000股\n(2)每單位價格：澳幣1元\n(3)交易總金額：增加澳幣60,000,000元(約新台幣1,278,000,000元)\r\n6.交易相對人及其與公司之關係（交易相對人如屬自然人，且非公司之\r\n關係人者，得免揭露其姓名）:\r\nDaiken Biomedical Australia Pty Ltd，本公司100%持有之子公司\r\n7.交易相對人為關係人者，並應公告選定關係人為交易對象之原因及前次移\r\n轉之所有人、前次移轉之所有人與公司及交易相對人間相互之關係、前次\r\n移轉日期及移轉金額:\r\n不適用\r\n8.交易標的最近五年內所有權人曾為公司之關係人者，尚應公告關係人之取\r\n得及處分日期、價格及交易當時與公司之關係:\r\n不適用\r\n9.本次係處分債權之相關事項（含處分之債權附隨擔保品種類、處分債權\r\n如有屬對關係人債權者尚需公告關係人名稱及本次處分該關係人之債權\r\n帳面金額:\r\n不適用\r\n10.處分利益（或損失）（取得有價證券者不適用）（原遞延者應列表說明\r\n認列情形）:\r\n不適用\r\n11.交付或付款條件（含付款期間及金額）、契約限制條款及其他重要約定\r\n事項:\r\n依子公司營運需求投入資金\r\n12.本次交易之決定方式、價格決定之參考依據及決策單位:\r\n董事會決議\r\n13.取得或處分有價證券標的公司每股淨值:\r\n不適用\r\n14.迄目前為止，累積持有本交易證券（含本次交易）之數量、金額、持股\r\n比例及權利受限情形（如質押情形）:\r\n(1)累積持有數量：75,000,000股\n(2)累積金額：澳幣75,000,000元(約新台幣1,597,500,000元)\n(3)持股比例：100%\n(4)權利受限情形：無\r\n15.迄目前為止，依「公開發行公司取得或處分資產處理準則」第三條所列\r\n之有價證券投資（含本次交易）占公司最近期財務報表中總資產及歸屬\r\n於母公司業主之權益之比例暨最近期財務報表中營運資金數額（註二）:\r\n(1)占總資產比率：103.89%\n(2)占歸屬於母公司業主之權益比率：29.87%\n(3)營運資金數額：新台幣1,254,103仟元\n(4)取得有價證券之資金來源：自有資金\r\n16.經紀人及經紀費用:\r\n不適用\r\n17.取得或處分之具體目的或用途:\r\n長期投資\r\n18.本次交易表示異議董事之意見:\r\n無\r\n19.本次交易為關係人交易:是\r\n20.監察人承認或審計委員會同意日期:\r\n民國115年1月21日\r\n21.本次交易會計師出具非合理性意見:不適用\r\n22.會計師事務所名稱:\r\n不適用\r\n23.會計師姓名:\r\n不適用\r\n24.會計師開業證書字號:\r\n不適用\r\n25.是否涉及營運模式變更:否\r\n26.營運模式變更說明:\r\n不適用\r\n27.過去一年及預計未來一年內與交易相對人交易情形:\r\n無\r\n28.資金來源:\r\n大研自有資金\r\n29.前已就同一件事件發布重大訊息日期: 不適用\r\n30.其他敘明事項:\r\n無"},
{"出表日期":"1150122","發言日期":"1150121","發言時間":"143923","公司代號":"1809","公司名稱":"中釉","主旨 ":"本公司因有價證券於集中市場達公布注意交易資訊標準\r\n，公布相關財務業務資訊，以利投資人區別瞭解","符合條款":"第51款","事實發生日":"1150121","說明":"1.事實發生日:115/01/21\n2.發生緣由:依臺灣證券交易所通知辦理\n3.財務業務資訊:\n科目           最近一月     與去年     最近一季     與去年   113年第4季至\n              114年12月    同期增減%  114年第3季   同期增減%  114年3季\n               自結數                   核閱數                 核閱數\n             =========     =========   =========   =======  ===========\n營業收入(百萬)  226         -4.64%        660       17.44%      2,504\n稅前淨利(百萬)    7        -68.18%          4      -78.95%         26\n歸屬母公司業主\n淨利(百萬)        6        -62.50%          4      -78.95%         29\n每股盈餘(元)   0.04        -55.56%       0.02      -83.33%       0.17\n4.有無「臺灣證券交易所股份有限公司對有價證券上市公司重大訊息之查證暨公開處理\n  程序」第4條所列重大訊息之情事（如「有」，請說明）:無\n5.有無「臺灣證券交易所股份有限公司對有價證券上市公司重大訊息之查證暨公開處理\n  程序」第11條所列重大訊息說明記者會之情事:無\n6.完整財務資訊請至公開資訊觀測站查閱，路徑如下：\n(1)近期營業收入及損益資訊：基本資料>精華版\n(2)歷史每月營業收入：營運概況>每月營收>採用IFRSs後之月營業收入資訊\n(3)歷史損益(會計師查核/核閱數)：財務報表>採IFRSs後>合併/個別報表>綜合損益表\n(4)歷史損益(自願性公告自結數)：營運概況>自結損益公告:\n7.其他應敘明事項:無"},
{"出表日期":"1150122","發言日期":"1150121","發言時間":"144927","公司代號":"2929","公司名稱":"淘帝-KY","主旨 ":"更正本公司114年12月資金貸與他人申報事項","符合條款":"第51款","事實發生日":"1150121","說明":"1.事實發生日:115/01/21\n2.公司名稱:淘帝國際控股有限公司\n3.與公司關係(請輸入本公司或子公司):本公司\n4.相互持股比例:不適用\n5.發生緣由:更正本公司114年12月之資金貸與他人事項之實際動支金額\n6.更正資訊項目/報表名稱:資金貸與資訊揭露明細表\n7.更正前金額/內容/頁次:\n貸出資金之公司/淘帝（中國）服飾有限公司/貸與對象/福建淘帝網絡科技有限公司\n實際動支金額/1,254新台幣仟元\n8.更正後金額/內容/頁次:\n貸出資金之公司/淘帝（中國）服飾有限公司/貸與對象/福建淘帝網絡科技有限公司\n實際動支金額/1,304新台幣仟元\n9.因應措施:以重大訊息說明，並同步更正資金貸與資訊揭露明細表。\n10.其他應敘明事項:無。"},
{"出表日期":"1150122","發言日期":"1150121","發言時間":"150444","公司代號":"5292","公司名稱":"華懋","主旨 ":"公告本公司代理發言人異動案","符合條款":"第8款","事實發生日":"1150121","說明":"1.人員變動別（請輸入發言人、代理發言人、重要營運主管(如:執行長、營運長、\n行銷長及策略長等)、財務主管、會計主管、公司治理主管、資訊安全長、研發主管、\n內部稽核主管或訴訟及非訟代理人）:代理發言人\n2.發生變動日期:115/01/21\n3.舊任者姓名、級職及簡歷:林國源、總經理\n4.新任者姓名、級職及簡歷:陳倫慶、業務/工程副總經理\n5.異動情形（請輸入「辭職」、「職務調整」、「資遣」、「退休」、「死亡」、「新\n任」或「解任」）:職務調整\n6.異動原因:職務調整\n7.生效日期:115/01/21\n8.其他應敘明事項:無"},
{"出表日期":"1150122","發言日期":"1150121","發言時間":"150716","公司代號":"1541","公司名稱":"錩泰","主旨 ":"公告本公司內部稽核主管異動","符合條款":"第8款","事實發生日":"1150121","說明":"1.人員變動別（請輸入發言人、代理發言人、重要營運主管(如:執行長、營運長、\n行銷長及策略長等)、財務主管、會計主管、公司治理主管、資訊安全長、研發主管、\n內部稽核主管或訴訟及非訟代理人）:內部稽核主管\n2.發生變動日期:115/01/21\n3.舊任者姓名、級職及簡歷:賈雨翰(暫代)/本公司專員\n4.新任者姓名、級職及簡歷:賈雨翰/本公司專員\n5.異動情形（請輸入「辭職」、「職務調整」、「資遣」、「退休」、「死亡」、「新\n任」或「解任」）:職務調整\n6.異動原因:職務調整\n7.生效日期:115/01/21\n8.其他應敘明事項:於115/01/21經審計委員會、董事會通過。"},
{"出表日期":"1150122","發言日期":"1150121","發言時間":"150830","公司代號":"1541","公司名稱":"錩泰","主旨 ":"公告本公司財務主管、會計主管、公司治理主管及發言人異動","符合條款":"第8款","事實發生日":"1150121","說明":"1.人員變動別（請輸入發言人、代理發言人、重要營運主管(如:執行長、營運長、\n行銷長及策略長等)、財務主管、會計主管、公司治理主管、資訊安全長、研發主管、\n內部稽核主管或訴訟及非訟代理人）:財務主管、會計主管、公司治理主管及發言人\n2.發生變動日期:115/01/21\n3.舊任者姓名、級職及簡歷:\n（1）財務主管、公司治理主管(暫代):劉姿妙/本公司副理\n（2）會計主管(暫代):林美君/本公司副理\n（3）發言人(暫代):賈雨翰/本公司專員\n4.新任者姓名、級職及簡歷:\n（1）財務主管、公司治理主管:劉姿妙/本公司副理\n（2）會計主管:林美君/本公司副理\n（3）發言人:賈雨翰/本公司專員\n5.異動情形（請輸入「辭職」、「職務調整」、「資遣」、「退休」、「死亡」、「新\n任」或「解任」）:職務調整\n6.異動原因:職務調整\n7.生效日期:115/01/21\n8.其他應敘明事項:於115/01/21經董事會通過"},
{"出表日期":"1150122","發言日期":"1150121","發言時間":"150846","公司代號":"3535","公司名稱":"晶彩科","主旨 ":"係因本公司有價證券於集中交易市場達公布注意交易資訊標\r\n準，故公布相關財務業務等重大訊息，以利投資人區別瞭解。","符合條款":"第51款","事實發生日":"1150121","說明":"1.事實發生日:115/01/21\n2.發生緣由:依據臺灣證券交易所股份有限公司通知辦理。\n3.財務業務資訊:\n期間          最近一月    與去年同    最近一季  與去年同    最近四季累計\n科目        114年12月    期增減%   114年第3季  期增減% 113年第4季至114年第3季\n         (IFRS合併自結數)        (IFRS合併核閱數)           (IFRS合併核閱數)\n============================================================================\n營業收入          84.41      959%       214.24       -64%           288.52\n(百萬元)\n稅前淨利          14.59      155%      -137.48      -284%          -157.59\n(百萬元)\n歸屬母公司淨利    14.59      155%      -137.21      -284%          -157.33\n(百萬元)\n每股盈餘           0.18      155%        -1.74      -284%            -1.99\n (元)\n4.有無「臺灣證券交易所股份有限公司對有價證券上市公司重大訊息之查證暨公開處理\n  程序」第4條所列重大訊息之情事（如「有」，請說明）:無\n5.有無「臺灣證券交易所股份有限公司對有價證券上市公司重大訊息之查證暨公開處理\n  程序」第11條所列重大訊息說明記者會之情事:無\n6.完整財務資訊請至公開資訊觀測站查閱，路徑如下：\n(1)近期營業收入及損益資訊：基本資料>精華版\n(2)歷史每月營業收入：營運概況>每月營收>採用IFRSs後之月營業收入資訊\n(3)歷史損益(會計師查核/核閱數)：財務報表>採IFRSs後>合併/個別報表>綜合損益表\n(4)歷史損益(自願性公告自結數)：營運概況>自結損益公告:\n7.其他應敘明事項:114年12月為本公司自結數，未經會計師查核。"},
{"出表日期":"1150122","發言日期":"1150121","發言時間":"150850","公司代號":"1541","公司名稱":"錩泰","主旨 ":"公告本公司資訊安全長異動","符合條款":"第8款","事實發生日":"1150121","說明":"1.人員變動別（請輸入發言人、代理發言人、重要營運主管(如:執行長、營運長、\n行銷長及策略長等)、財務主管、會計主管、公司治理主管、資訊安全長、研發主管、\n內部稽核主管或訴訟及非訟代理人）:資訊安全長\n2.發生變動日期:115/01/21\n3.舊任者姓名、級職及簡歷:從缺\n4.新任者姓名、級職及簡歷:黃荏金丙先生\n5.異動情形（請輸入「辭職」、「職務調整」、「資遣」、「退休」、「死亡」、「新\n任」或「解任」）:新任\n6.異動原因:新任\n7.生效日期:115/01/21\n8.其他應敘明事項:於115/01/21經審計委員會、董事會通過。"},
{"出表日期":"1150122","發言日期":"1150121","發言時間":"151020","公司代號":"2891","公司名稱":"中信金","主旨 ":"子公司中信銀公告香港分行發行美元計價股權連結\r\n固定收益型結構型債券共2筆","符合條款":"第11款","事實發生日":"1150121","說明":"1.董事會決議日期:NA\n2.名稱﹝XX公司第X次（有、無）擔保公司債﹞:\n第1筆:中國信託商業銀行股份有限公司香港分行6個月期美元計價\n提前出場一籃子股權連結固定收益型結構型債券(無保證機構)(無擔保)(不保本)\n第2筆:中國信託商業銀行股份有限公司香港分行7個月期美元計價\n提前出場一籃子股權連結固定收益型結構型債券(無保證機構)(無擔保)(不保本)\n3.是否採總括申報發行公司債(是/否):否\n4.發行總額:美元300,000元整\n5.每張面額:美元10,000元\n6.發行價格:於發行日按債券面額十足發行\n7.發行期間:\n第1筆:6個月，\n第2筆:7個月，\n惟債券條件另有約定者依其約定。\n8.發行利率:\n第1筆:固定年利率22.13%\n第2筆:固定年利率19.68%\n9.擔保品之種類、名稱、金額及約定事項:無\n10.募得價款之用途及運用計畫:支應本行香港分行業務需求並充實流動性\n11.承銷方式:無\n12.公司債受託人:無\n13.承銷或代銷機構:無\n14.發行保證人:無\n15.代理還本付息機構:The Hongkong and Shanghai Banking Corporation Limited。\n16.簽證機構:無\n17.能轉換股份者，其轉換辦法:不適用\n18.賣回條件:無\n19.買回條件:中信銀香港分行有權於約定事件發生時，提前贖回本債券。\n20.附有轉換、交換或認股者，其換股基準日:不適用\n21.附有轉換、交換或認股者，對股權可能稀釋情形:不適用\n22.其他應敘明事項:\n第1筆:ISIN:XS3278609253\n第2筆:ISIN:XS3279617644"},
{"出表日期":"1150122","發言日期":"1150121","發言時間":"153844","公司代號":"2233","公司名稱":"宇隆","主旨 ":"代子公司東莞信豐五金機械塑膠工業有限公司公告取得\r\n不動產之使用權資產","符合條款":"第20款","事實發生日":"1150121","說明":"1.標的物之名稱及性質（如坐落台中市北區ＸＸ段ＸＸ小段土地）:\r\n東莞市長安鎮上角社區上興路45號廠房、宿舍及64號宿舍\r\n2.事實發生日:115/1/21~115/1/21\r\n3.董事會通過日期: 民國115年1月21日\r\n4.其他核決日期: 不適用\r\n5.交易單位數量（如ＸＸ平方公尺，折合ＸＸ坪）、每單位價格及交易總金額:\r\n交易單位數量：租賃面積為30,344.92平方公尺，折合約9,179.34坪\n每單位價格：前三年每月租金為人民幣575,639.68元(未稅)；第四至第五年每月\n租金為人民幣606,879.58元(未稅)\n交易總金額：租期之租金合計人民幣35,288,138.40元(未稅)\n使用權資產金額：人民幣32,294,030.63元\r\n6.交易相對人及其與公司之關係（交易相對人如屬自然人，且非公司之關\r\n係人者，得免揭露其姓名）:\r\n交易相對人：東莞市長安鎮上角股份經濟聯合社\n與公司關係：無\r\n7.交易相對人為關係人者，並應公告選定關係人為交易對象之原因及前次移轉之\r\n所有人、前次移轉之所有人與公司及交易相對人間相互之關係、前次移轉日期\r\n及移轉金額:\r\n不適用\r\n8.交易標的最近五年內所有權人曾為公司之關係人者，尚應公告關係\r\n人之取得及處分日期、價格及交易當時與公司之關係:\r\n不適用\r\n9.預計處分利益（或損失）（取得資產者不適用）（遞延者應列表說明\r\n認列情形）:\r\n不適用\r\n10.交付或付款條件（含付款期間及金額）、契約限制條款及其他重要約定\r\n事項:\r\n付款金額：前三年每月租金為人民幣575,639.68元(未稅)；\n第四至第五年每月租金為人民幣606,879.58元(未稅)\n付款條件：月繳\n租期：民國115年02月01日至民國120年01月31日\r\n11.本次交易之決定方式（如招標、比價或議價）、價格決定之參考依據及\r\n決策單位:\r\n交易之決定方式：議價\n價格決定之參考依據：估價報告及議價結果\n決策單位：董事會\r\n12.專業估價者事務所或公司名稱及其估價金額:\r\n專業估價者事務所名稱：華淵不動產估價師事務所\n估價金額：合理建物租金區間為每月人民幣546,000元~ 668,000元\r\n13.專業估價師姓名:\r\n陳聯興\r\n14.專業估價師開業證書字號:\r\n(一○一)高市估字第000068號(換發)\r\n15.估價報告是否為限定價格、特定價格或特殊價格:否或不適用\r\n16.是否尚未取得估價報告:否或不適用\r\n17.尚未取得估價報告之原因:\r\n不適用\r\n18.估價結果有重大差異時，其差異原因及會計師意見:\r\n不適用\r\n19.會計師事務所名稱:\r\n不適用\r\n20.會計師姓名:\r\n不適用\r\n21.會計師開業證書字號:\r\n不適用\r\n22.經紀人及經紀費用:\r\n不適用\r\n23.取得或處分之具體目的或用途:\r\n因應營運需求\r\n24.本次交易表示異議之董事之意見:\r\n無\r\n25.本次交易為關係人交易:否\r\n26.監察人承認或審計委員會同意日期:\r\n民國115年1月21日\r\n27.本次交易係向關係人取得不動產或其使用權資產:否\r\n28.依「公開發行公司取得或處分資產處理準則」第十六條規定\r\n評估之價格:不適用\r\n29.依前項評估之價格較交易價格為低者，依同準則第十七條規\r\n定評估之價格:不適用\r\n30.前已就同一件事件發布重大訊息日期: 不適用\r\n31.其他敘明事項:\r\n授權董事長就交易總金額正負5%範圍內，依「取得或處分資產管理辦法」\n處理該項交易相關事宜，同時使用權資產及估價報告書依最終承租金額計算；\n若逾授權金額，事後再予以提報董事會追認。"},
{"出表日期":"1150122","發言日期":"1150121","發言時間":"153954","公司代號":"2233","公司名稱":"宇隆","主旨 ":"代子公司浙江宇鑽精密元件有限公司公告自地委建興建新廠營建工程預算","符合條款":"第20款","事實發生日":"1150121","說明":"1.契約種類:自地委建契約\r\n2.事實發生日:115/1/21~115/1/21\r\n3.董事會通過日期: 民國115年1月21日\r\n4.其他核決日期: 不適用\r\n5.契約相對人及其與公司之關係:\r\n契約相對人待確定，非關係人。\r\n6.契約主要內容（含契約總金額、預計參與投入之金額及契約起迄日期）\r\n、限制條款及其他重要約定事項:\r\n新廠營建工程預算人民幣230,000仟元\r\n7.專業估價者事務所或公司名稱及其估價結果:\r\n不適用\r\n8.不動產估價師姓名:\r\n不適用\r\n9.不動產估價師開業證書字號:\r\n不適用\r\n10.取得之具體目的:\r\n因應未來營運發展規劃及產能需求\r\n11.本次交易表示異議之董事意見:\r\n無\r\n12.本次交易為關係人交易:否\r\n13.監察人承認或審計委員會同意日期:\r\n民國115年1月21日\r\n14.估價報告是否為限定價格、特定價格或特殊價格:否或不適用\r\n15.是否尚未取得估價報告:否或不適用\r\n16.尚未取得估價報告之原因:\r\n不適用\r\n17.估價結果有重大差異時，其差異原因及會計師意見:\r\n不適用\r\n18.會計師事務所名稱:\r\n不適用\r\n19.會計師姓名:\r\n不適用\r\n20.會計師開業證書字號:\r\n不適用\r\n21.前已就同一件事件發布重大訊息日期: 不適用\r\n22.其他敘明事項:\r\n無"},
{"出表日期":"1150122","發言日期":"1150121","發言時間":"154122","公司代號":"2233","公司名稱":"宇隆","主旨 ":"公告本公司國內第一次無擔保轉換公司債收足債款","符合條款":"第51款","事實發生日":"1150121","說明":"1.事實發生日:115/01/21\n2.公司名稱:宇隆科技股份有限公司\n3.與公司關係(請輸入本公司或子公司):本公司\n4.相互持股比例:不適用\n5.發生緣由:依據「發行人募集與發行有價證券處理準則」第九條第一項第二款規定辦理\n公告，本公司發行國內第一次無擔保轉換公司債至公告日止，債款代收銀行業已收足所\n有應募款項共計新臺幣1,313,000,000元整，並匯撥至存儲專戶銀行，特此公告。\n6.因應措施:無\n7.其他應敘明事項(若事件發生或決議之主體係屬公開發行以上公司，本則重大訊息同時\n  符合證券交易法施行細則第7條第9款所定對股東權益或證券價格有重大影響之事項):\n無"},
{"出表日期":"1150122","發言日期":"1150121","發言時間":"155549","公司代號":"1526","公司名稱":"日馳","主旨 ":"係因本公司有價證券於集中交易市場達公佈注意交易資訊標準\r\n故公佈相關財務,業務等重大訊息,以利投資人區別瞭解","符合條款":"第51款","事實發生日":"1150121","說明":"1.事實發生日:115/01/21\n2.發生緣由:依據臺灣證券交易所股份有限公司通知辦理\n3.財務業務資訊:\n期間          (  月  )             (   季   )          (最近四季累計)\n======== =================== ====================== ====================\n          最近一月  與去年     最近一季    與去年\n科目      114年12月 同期增減   114年第3季  同期增減   113第4季至114第3季\n            IFRS     (%)         IFRS       (%)             IFRS\n           自結數               核閱數                     核閱數\n======== ========= ========= =========== ========== ====================\n營業收入    59.07     15.06%      202.39     26.30%          788.17\n(百萬)\n稅前淨利     3.69    114.82%        6.50   -115.80%          -32.41\n(百萬)\n本期淨利     2.75    113.65%        4.64   -115.28%          -28.59\n(百萬)\n每股盈餘     0.05    118.18%        0.08   -115.69%          - 0.47\n4.有無「臺灣證券交易所股份有限公司對有價證券上市公司重大訊息之查證暨公開處理\n  程序」第4條所列重大訊息之情事（如「有」，請說明）:無\n5.有無「臺灣證券交易所股份有限公司對有價證券上市公司重大訊息之查證暨公開處理\n  程序」第11條所列重大訊息說明記者會之情事:無\n6.完整財務資訊請至公開資訊觀測站查閱，路徑如下：\n(1)近期營業收入及損益資訊：基本資料>精華版\n(2)歷史每月營業收入：營運概況>每月營收>採用IFRSs後之月營業收入資訊\n(3)歷史損益(會計師查核/核閱數)：財務報表>採IFRSs後>合併/個別報表>綜合損益表\n(4)歷史損益(自願性公告自結數)：營運概況>自結損益公告:\n7.其他應敘明事項:無"},
{"出表日期":"1150122","發言日期":"1150121","發言時間":"160109","公司代號":"8404","公司名稱":"百和興業-KY","主旨 ":"公告本公司召開法人說明會之相關資訊","符合條款":"第12款","事實發生日":"1150122","說明":"符合條款第四條第XX款：12\r\n事實發生日：115/01/22\r\n1.召開法人說明會之日期：115/01/22\r\n2.召開法人說明會之時間：14 時 00 分 \r\n3.召開法人說明會之地點：本公司台灣辦事處所在地(彰化縣和美鎮和港路575號)\r\n4.法人說明會擇要訊息：本公司召開法人說明會，說明本公司財務業務狀況及經營績效。\r\n5.其他應敘明事項：無\r\n完整財務業務資訊請至公開資訊觀測站之法人說明會一覽表或法說會項目下查閱。"},
{"出表日期":"1150122","發言日期":"1150121","發言時間":"160146","公司代號":"3049","公司名稱":"精金","主旨 ":"本公司因有價證券於集中交易市場達公布注意交易資訊標準，\r\n故公布相關財務業務等重大訊息，以利投資人區別瞭解","符合條款":"第51款","事實發生日":"1150121","說明":"1.事實發生日:115/01/21\n2.發生緣由:依臺灣證券交易所通知辦理。\n3.財務業務資訊:\n\n 期  間            月                     季                 最近四季累計\n--------   ---------------------   ---------------------   -----------------\n            最近一月    與去年同   最近一季     與去年同      113年第4季\n 科  目     114年11月   期增減％   114年第3季   期增減％     至114年第3季\n             (合併財報自結數)        (合併財報核閱數)       (合併財報核閱數)\n--------   ---------------------   ---------------------   -----------------\n營業收入       153       -1.92%       334       -21.23%           1,449\n(百萬)\n\n稅前淨利        40      165.57%      -151        53.11%            -658\n(百萬)\n\n歸屬於母公司\n業主淨利        34      157.63%      -151        49.50%            -686\n(百萬)\n\n每股盈餘      0.04      158.47%     -0.19        48.65%           -0.86\n(元)\n\n4.有無「臺灣證券交易所股份有限公司對有價證券上市公司重大訊息之查證暨公開處理\n  程序」第4條所列重大訊息之情事（如「有」，請說明）:無。\n5.有無「臺灣證券交易所股份有限公司對有價證券上市公司重大訊息之查證暨公開處理\n  程序」第11條所列重大訊息說明記者會之情事:無。\n6.完整財務資訊請至公開資訊觀測站查閱，路徑如下：\n(1)近期營業收入及損益資訊：基本資料>精華版\n(2)歷史每月營業收入：營運概況>每月營收>採用IFRSs後之月營業收入資訊\n(3)歷史損益(會計師查核/核閱數)：財務報表>採IFRSs後>合併/個別報表>綜合損益表\n(4)歷史損益(自願性公告自結數)：營運概況>自結損益公告:\n7.其他應敘明事項:無。"},
{"出表日期":"1150122","發言日期":"1150121","發言時間":"160334","公司代號":"1802","公司名稱":"台玻","主旨 ":"係因本公司有價證券於集中交易市場達公布注意交易資訊\r\n標準，故公布相關財務業務等重大訊息，以利投資人區別瞭解","符合條款":"第51款","事實發生日":"1150121","說明":"1.事實發生日:115/01/21\n2.發生緣由:依臺灣證券交易所股份有限公司通知辦理\n3.財務業務資訊:\n                         最近一月\n科目                     114年11月           與去年同期增減(%)\n                       (合併自結數)\n營業收入(百萬元)          3,604                    (7)%\n稅前淨利(百萬元)            274                    265%\n歸屬母公司業主淨利\n        (百萬元)            234                    251%\n每股盈餘(元)               0.08                    260%\n\n                          最近一季\n科目                    114年第三季         與去年同期增減(%)\n                        (合併核閱數)\n營業收入(百萬元)          10,727                     6%\n稅前淨利(百萬元)             308                   126%\n歸屬母公司業主淨利\n        (百萬元)             277                   125%\n每股盈餘(元)                0.10                   126%\n\n                      最近四季累計\n科目              113年第四季至114年第三季\n                        (合併核閱數)\n營業收入(百萬元)          42,263\n稅前淨利(百萬元)          (1,091)\n歸屬母公司業主淨利\n        (百萬元)          (1,007)\n每股盈餘(元)               (0.35)\n\n4.有無「臺灣證券交易所股份有限公司對有價證券上市公司重大訊息之查證暨公開處理\n  程序」第4條所列重大訊息之情事（如「有」，請說明）:無。\n5.有無「臺灣證券交易所股份有限公司對有價證券上市公司重大訊息之查證暨公開處理\n  程序」第11條所列重大訊息說明記者會之情事:無。\n6.完整財務資訊請至公開資訊觀測站查閱，路徑如下：\n(1)近期營業收入及損益資訊：基本資料>精華版\n(2)歷史每月營業收入：營運概況>每月營收>採用IFRSs後之月營業收入資訊\n(3)歷史損益(會計師查核/核閱數)：財務報表>採IFRSs後>合併/個別報表>綜合損益表\n(4)歷史損益(自願性公告自結數)：營運概況>自結損益公告:\n7.其他應敘明事項:114年11月為自結報表，實際以會計師核閱數為準。"},
{"出表日期":"1150122","發言日期":"1150121","發言時間":"161040","公司代號":"3543","公司名稱":"州巧","主旨 ":"公告本公司114年現金增資發行新股已依中國證監會發布之\r\n「境內企業境外發行證券和上市管理試行辦法」進\r\n行備案","符合條款":"第51款","事實發生日":"1150121","說明":"1.事實發生日:115/01/21\n2.公司名稱:州巧科技股份有限公司\n3.與公司關係(請輸入本公司或子公司):本公司\n4.相互持股比例:不適用\n5.發生緣由:因應中國證券監督管理委員會發布之「境內企業境外發行證券和上市管理\n試行辦法」(以下稱「試行辦法」)辦理。\n6.因應措施:本公司因辦理114年現金增資發行新股，依中國證券監督管理委員會發布\n之「境內企業境外發行證券和上市管理試行辦法」規定，已於115年1月21日向中國\n證監會進行備案。\n7.其他應敘明事項(若事件發生或決議之主體係屬公開發行以上公司，本則重大訊息同時\n  符合證券交易法施行細則第7條第9款所定對股東權益或證券價格有重大影響之事項):無"},
{"出表日期":"1150122","發言日期":"1150121","發言時間":"161145","公司代號":"6451","公司名稱":"訊芯-KY","主旨 ":"公告本公司修訂「中華民國境內第二次無擔保轉換公司債\r\n發行及轉換辦法」業經金融監督管理委員會核准","符合條款":"第51款","事實發生日":"1150121","說明":"1.事實發生日:115/01/21\n2.公司名稱:訊芯科技控股股份有限公司\n3.與公司關係(請輸入本公司或子公司):本公司\n4.相互持股比例:不適用\n5.發生緣由:\n  本公司依金融監督管理委員會民國114年5月5日金管證發字第1140382105號函規定，\n  修訂「中華民國境內第二次無擔保轉換公司債發行及轉換辦法」案，業經金融監督\n  管理委員會115年1月20日金管證發字第1150331201號函核備在案。\n6.因應措施:無。\n7.其他應敘明事項(若事件發生或決議之主體係屬公開發行以上公司，本則重大訊息同時\n  符合證券交易法施行細則第7條第9款所定對股東權益或證券價格有重大影響之事項):\n  本公司經申報核准後完整「中華民國境內第二次無擔保轉換公司債發行及轉換辦法」\n  ，請至公開資訊觀測站「債券發行資訊查詢」。"},
{"出表日期":"1150122","發言日期":"1150121","發言時間":"162420","公司代號":"6928","公司名稱":"攸泰科技","主旨 ":"公告本公司內部稽核主管異動","符合條款":"第8款","事實發生日":"1150121","說明":"1.人員變動別（請輸入發言人、代理發言人、重要營運主管(如:執行長、營運長、\n行銷長及策略長等)、財務主管、會計主管、公司治理主管、資訊安全長、研發主管、\n內部稽核主管或訴訟及非訟代理人）:內部稽核主管\n2.發生變動日期:115/01/21\n3.舊任者姓名、級職及簡歷:邱皇淳資深經理，本公司內部稽核主管\n4.新任者姓名、級職及簡歷:待補\n5.異動情形（請輸入「辭職」、「職務調整」、「資遣」、「退休」、「死亡」、「新\n任」或「解任」）:辭職\n6.異動原因:辭職\n7.生效日期:115/02/06\n8.其他應敘明事項:無"},
{"出表日期":"1150122","發言日期":"1150121","發言時間":"163036","公司代號":"2610","公司名稱":"華航","主旨 ":"桃園市政府勞動局裁處罰鍰新台幣200萬元","符合條款":"第26款","事實發生日":"1150121","說明":"1.事實發生日：115/01/21\r\n2.事實發生主體：本公司\r\n3.發生緣由(事件說明)：桃園市政府勞動局於114年12月3日實施勞動檢查，以本公司飛航組員派飛工時\r\n超過一日工時上限12小時、兩人派遣未安排休時，違反勞動基準法第32條第2\r\n項、第35條規定，共計裁處罰鍰新臺幣200萬元。\r\n4.處理過程：依裁處書規定期限內繳納罰鍰\r\n5.處分情形：行政罰鍰\r\n6.是否遭裁處罰鍰：是\r\n7.裁罰金額(元)：新台幣 2,000,000 元\r\n8.預計可能損失或影響：罰鍰新台幣2,000,000元\r\n9.可能獲得保險理賠之金額(元)：不適用\r\n10.改善情形及未來因應措施：本公司向來重視組員身心健康，組員派遣均依民航法規辦理。\r\n本案係因法規扞格所致，將依法提起行政救濟，請求撤銷處分。\r\n11.是否前已就同一事件發布重大訊息：否\r\n12.其他應述明事項：無"},
{"出表日期":"1150122","發言日期":"1150121","發言時間":"163947","公司代號":"3711","公司名稱":"日月光投控","主旨 ":"代子公司日月光半導體製造(股)公司公告\r\n取得Lam Research International Sdn. Bhd供營業用之機器設備","符合條款":"第20款","事實發生日":"1150121","說明":"1.標的物之名稱及性質（如坐落台中市北區ＸＸ段ＸＸ小段土地）:\r\n供營業用之機器設備\r\n2.事實發生日:114/12/16~115/1/21\r\n3.董事會通過日期: 不適用\r\n4.其他核決日期:\r\n核決層級:總經理核決\r\n民國115年1月21日\r\n5.交易單位數量（如ＸＸ平方公尺，折合ＸＸ坪）、每單位價格及交易總金額:\r\n交易數量：一批\n每單位價格計：新台幣1,059,373仟元(未稅)\n累計交易總金額計：新台幣1,059,373仟元(未稅)\r\n6.交易相對人及其與公司之關係（交易相對人如屬自然人，且非公司之關\r\n係人者，得免揭露其姓名）:\r\n交易相對人：Lam Research International Sdn. Bhd\n與公司之關係：無\r\n7.交易相對人為關係人者，並應公告選定關係人為交易對象之原因及前次移轉之\r\n所有人、前次移轉之所有人與公司及交易相對人間相互之關係、前次移轉日期\r\n及移轉金額:\r\n不適用\r\n8.交易標的最近五年內所有權人曾為公司之關係人者，尚應公告關係\r\n人之取得及處分日期、價格及交易當時與公司之關係:\r\n不適用\r\n9.預計處分利益（或損失）（取得資產者不適用）（遞延者應列表說明\r\n認列情形）:\r\n不適用\r\n10.交付或付款條件（含付款期間及金額）、契約限制條款及其他重要約定\r\n事項:\r\n交付或付款條件：電匯或信用狀付款\n契約限制條款：無\n其他重要約定事項：無\r\n11.本次交易之決定方式（如招標、比價或議價）、價格決定之參考依據及\r\n決策單位:\r\n交易之決定方式及價格決定之參考依據：比價及議價\n決策單位：依該公司核決權限規定辦理\r\n12.專業估價者事務所或公司名稱及其估價金額:\r\n不適用\r\n13.專業估價師姓名:\r\n不適用\r\n14.專業估價師開業證書字號:\r\n不適用\r\n15.估價報告是否為限定價格、特定價格或特殊價格:否或不適用\r\n16.是否尚未取得估價報告:否或不適用\r\n17.尚未取得估價報告之原因:\r\n不適用\r\n18.估價結果有重大差異時，其差異原因及會計師意見:\r\n不適用\r\n19.會計師事務所名稱:\r\n不適用\r\n20.會計師姓名:\r\n不適用\r\n21.會計師開業證書字號:\r\n不適用\r\n22.經紀人及經紀費用:\r\n無\r\n23.取得或處分之具體目的或用途:\r\n供生產及營運用\r\n24.本次交易表示異議之董事之意見:\r\n不適用\r\n25.本次交易為關係人交易:否\r\n26.監察人承認或審計委員會同意日期:\r\n不適用\r\n27.本次交易係向關係人取得不動產或其使用權資產:否\r\n28.依「公開發行公司取得或處分資產處理準則」第十六條規定\r\n評估之價格:不適用\r\n29.依前項評估之價格較交易價格為低者，依同準則第十七條規\r\n定評估之價格:不適用\r\n30.前已就同一件事件發布重大訊息日期: 不適用\r\n31.其他敘明事項:\r\n無"},
{"出表日期":"1150122","發言日期":"1150121","發言時間":"164030","公司代號":"3711","公司名稱":"日月光投控","主旨 ":"代子公司日月光半導體製造(股)公司公告\r\n取得詠翰工程有限公司供營業用之廠務工程","符合條款":"第20款","事實發生日":"1150121","說明":"1.標的物之名稱及性質（如坐落台中市北區ＸＸ段ＸＸ小段土地）:\r\n供營業用之廠務工程\r\n2.事實發生日:114/1/22~115/1/21\r\n3.董事會通過日期: 不適用\r\n4.其他核決日期:\r\n核決層級:總經理核決\r\n民國115年1月21日\r\n5.交易單位數量（如ＸＸ平方公尺，折合ＸＸ坪）、每單位價格及交易總金額:\r\n交易數量：一批\n每單位價格計：新台幣300,334仟元(未稅)\n累計交易總金額計：新台幣300,334仟元(未稅)\r\n6.交易相對人及其與公司之關係（交易相對人如屬自然人，且非公司之關\r\n係人者，得免揭露其姓名）:\r\n交易相對人：詠翰工程有限公司\n與公司之關係：無\r\n7.交易相對人為關係人者，並應公告選定關係人為交易對象之原因及前次移轉之\r\n所有人、前次移轉之所有人與公司及交易相對人間相互之關係、前次移轉日期\r\n及移轉金額:\r\n不適用\r\n8.交易標的最近五年內所有權人曾為公司之關係人者，尚應公告關係\r\n人之取得及處分日期、價格及交易當時與公司之關係:\r\n不適用\r\n9.預計處分利益（或損失）（取得資產者不適用）（遞延者應列表說明\r\n認列情形）:\r\n不適用\r\n10.交付或付款條件（含付款期間及金額）、契約限制條款及其他重要約定\r\n事項:\r\n交付或付款條件：電匯或信用狀付款\n契約限制條款：無\n其他重要約定事項：無\r\n11.本次交易之決定方式（如招標、比價或議價）、價格決定之參考依據及\r\n決策單位:\r\n交易之決定方式及價格決定之參考依據：比價及議價\n決策單位：依該公司核決權限規定辦理\r\n12.專業估價者事務所或公司名稱及其估價金額:\r\n不適用\r\n13.專業估價師姓名:\r\n不適用\r\n14.專業估價師開業證書字號:\r\n不適用\r\n15.估價報告是否為限定價格、特定價格或特殊價格:否或不適用\r\n16.是否尚未取得估價報告:否或不適用\r\n17.尚未取得估價報告之原因:\r\n不適用\r\n18.估價結果有重大差異時，其差異原因及會計師意見:\r\n不適用\r\n19.會計師事務所名稱:\r\n不適用\r\n20.會計師姓名:\r\n不適用\r\n21.會計師開業證書字號:\r\n不適用\r\n22.經紀人及經紀費用:\r\n無\r\n23.取得或處分之具體目的或用途:\r\n供生產及營運用\r\n24.本次交易表示異議之董事之意見:\r\n不適用\r\n25.本次交易為關係人交易:否\r\n26.監察人承認或審計委員會同意日期:\r\n不適用\r\n27.本次交易係向關係人取得不動產或其使用權資產:否\r\n28.依「公開發行公司取得或處分資產處理準則」第十六條規定\r\n評估之價格:不適用\r\n29.依前項評估之價格較交易價格為低者，依同準則第十七條規\r\n定評估之價格:不適用\r\n30.前已就同一件事件發布重大訊息日期: 不適用\r\n31.其他敘明事項:\r\n無"},
{"出表日期":"1150122","發言日期":"1150121","發言時間":"165535","公司代號":"2454","公司名稱":"聯發科","主旨 ":"本公司於115/2/4召開第四季財報暨營運線上說明會","符合條款":"第12款","事實發生日":"1150204","說明":"符合條款第四條第XX款：12\r\n事實發生日：115/02/04\r\n1.召開法人說明會之日期：115/02/04\r\n2.召開法人說明會之時間：15 時 00 分 \r\n3.召開法人說明會之地點：線上法說會\r\n4.法人說明會擇要訊息：&#8206;(1) 公布本公司2025年第4季財務報告及2026年第1季業績展望。 (2) 參加方式：請參見https://www.mediatek.com/zh-&#8206;tw/investor-relations/financial-information#quarterly-earnings-&#8206;release &#8206;\r\n5.其他應敘明事項：無\r\n完整財務業務資訊請至公開資訊觀測站之法人說明會一覽表或法說會項目下查閱。"},
{"出表日期":"1150122","發言日期":"1150121","發言時間":"165701","公司代號":"2891","公司名稱":"中信金","主旨 ":"代子公司中國信託商業銀行公告授信資產之轉讓","符合條款":"第20款","事實發生日":"1150121","說明":"1.標的物之名稱及性質（屬特別股者，並應標明特別股約定發行條件，如股息率等）:\r\n金融機構債權(放款)\r\n2.事實發生日:115/1/21~115/1/21\r\n3.董事會通過日期: 不適用\r\n4.其他核決日期:\r\n核決層級:資深授信人\r\n民國114年10月22日\r\n5.交易單位數量、每單位價格及交易總金額:\r\n不適用\r\n不適用\r\nUSD10,000,000\r\n6.交易相對人及其與公司之關係（交易相對人如屬自然人，且非公司之\r\n關係人者，得免揭露其姓名）:\r\n永豐商業銀行\r\n非關係人。\r\n7.交易相對人為關係人者，並應公告選定關係人為交易對象之原因及前次移\r\n轉之所有人、前次移轉之所有人與公司及交易相對人間相互之關係、前次\r\n移轉日期及移轉金額:\r\n不適用\r\n8.交易標的最近五年內所有權人曾為公司之關係人者，尚應公告關係人之取\r\n得及處分日期、價格及交易當時與公司之關係:\r\n不適用\r\n9.本次係處分債權之相關事項（含處分之債權附隨擔保品種類、處分債權\r\n如有屬對關係人債權者尚需公告關係人名稱及本次處分該關係人之債權\r\n帳面金額:\r\n不適用\r\n10.處分利益（或損失）（取得有價證券者不適用）（遞延者應列表說明\r\n認列情形）:\r\n無。\r\n11.交付或付款條件（含付款期間及金額）、契約限制條款及其他重要約定\r\n事項:\r\n付款條件: 依合約辦理。\r\n重要約定事項: 依合約辦理。\r\n12.本次交易之決定方式、價格決定之參考依據及決策單位:\r\n為本行內部最終審核單位核定，相關條件依合約及一般市場慣例為之。\r\n13.取得或處分有價證券標的公司每股淨值:\r\n不適用\r\n14.迄目前為止，累積持有本交易證券（含本次交易）之數量、金額、持股\r\n比例及權利受限情形（如質押情形）:\r\n不適用\r\n15.迄目前為止，依「公開發行公司取得或處分資產處理準則」第三條所列\r\n之有價證券投資（含本次交易）占公司最近期財務報表中總資產及歸屬\r\n於母公司業主之權益之比例暨最近期財務報表中營運資金數額:\r\n不適用\r\n16.經紀人及經紀費用:\r\n不適用\r\n17.取得或處分之具體目的或用途:\r\n活絡債權資產組合。\r\n18.本次交易表示異議董事之意見:\r\n不適用\r\n19.本次交易為關係人交易:否\r\n20.監察人承認或審計委員會同意日期:\r\n不適用\r\n21.本次交易會計師出具非合理性意見:不適用\r\n22.會計師事務所名稱:\r\n不適用\r\n23.會計師姓名:\r\n不適用\r\n24.會計師開業證書字號:\r\n不適用\r\n25.是否涉及營運模式變更:否\r\n26.營運模式變更說明:\r\n不適用\r\n27.過去一年及預計未來一年內與交易相對人交易情形:\r\n例行性業務。\r\n28.資金來源:\r\n不適用\r\n29.前已就同一件事件發布重大訊息日期: 不適用\r\n30.其他敘明事項:\r\n本交易係依115/1/20之匯率計算(USD 1=NTD 31.609)。"},
{"出表日期":"1150122","發言日期":"1150121","發言時間":"170706","公司代號":"8499","公司名稱":"鼎炫-KY","主旨 ":"代&#12070;公司隆揚電&#12070;(昆&#12077;)股份有限公司公告處分結構式存款商品","符合條款":"第20款","事實發生日":"1150121","說明":"1.標的物之名稱及性質（屬特別股者，並應標明特別股約定發行條件，如股息率等）:\r\n廣發證券收益憑證收益寶16號\r\n2.事實發生日:115/1/21~115/1/21\r\n3.董事會通過日期: 不適用\r\n4.其他核決日期:\r\n核決層級:依公司核決權限辦理\r\n民國115年1月21日\r\n5.交易數量、每單位價格及交易總金額:\r\n收益寶16號 272天 ：&#12040;&#11936;幣2000萬元\r\n6.交易相對人及其與公司之關係（交易相對人如屬自然人，且非公司之\r\n關係人者，得免揭露其姓名）:\r\n廣發證券股份有限公司；與本公司關係：無\r\n7.交易相對人為關係人者，並應公告選定關係人為交易對象之原因及前次移\r\n轉之所有人、前次移轉之所有人與公司及交易相對人間相互之關係、前次\r\n移轉日期及移轉金額:\r\n不適用\r\n8.交易標的最近五年內所有權人曾為公司之關係人者，尚應公告關係人之取\r\n得及處分日期、價格及交易當時與公司之關係:\r\n不適用\r\n9.本次係處分債權之相關事項（含處分之債權附隨擔保品種類、處分債權\r\n如有屬對關係人債權者尚需公告關係人名稱及本次處分該關係人之債權\r\n帳面金額:\r\n不適用\r\n10.處分利益（或損失）（取得有價證券者不適用）（原遞延者應列表說明\r\n認列情形）:\r\n約台幣260仟元\r\n11.交付或付款條件（含付款期間及金額）、契約限制條款及其他重要約定\r\n事項:\r\n一次付清\r\n12.本次交易之決定方式、價格決定之參考依據及決策單位:\r\n依公司核決權限辦理\r\n13.取得或處分有價證券標的公司每股淨值:\r\n不適用\r\n14.迄目前為止，累積持有本交易證券（含本次交易）之數量、金額、持股\r\n比例及權利受限情形（如質押情形）:\r\n數量：不適&#12132;\n&#12198;額：&#12040;&#11936;幣2,000萬\n持股&#12112;例：不適&#12132;\n權利受限情形：無\n累計持有&#12198;額：&#12040;&#11936;幣2,000萬\r\n15.迄目前為止，依「公開發行公司取得或處分資產處理準則」第三條所列\r\n之有價證券投資（含本次交易）占公司最近期財務報表中總資產及歸屬\r\n於母公司業主之權益之比例暨最近期財務報表中營運資金數額（註二）:\r\n(1)占總資產&#12112;例：20.406%\n(2)占歸屬於&#11935;公司業主之權益&#12112;例：40.511%\n(3)營運資&#12198;數額：新台幣5,316,266仟元\r\n16.經紀人及經紀費用:\r\n不適用\r\n17.取得或處分之具體目的或用途:\r\n短期投資\r\n18.本次交易表示異議董事之意見:\r\n不適用\r\n19.本次交易為關係人交易:否\r\n20.監察人承認或審計委員會同意日期:\r\n不適用\r\n21.本次交易會計師出具非合理性意見:不適用\r\n22.會計師事務所名稱:\r\n不適用\r\n23.會計師姓名:\r\n不適用\r\n24.會計師開業證書字號:\r\n不適用\r\n25.是否涉及營運模式變更:否\r\n26.營運模式變更說明:\r\n不適用\r\n27.過去一年及預計未來一年內與交易相對人交易情形:\r\n不適用\r\n28.資金來源:\r\n自有資金\r\n29.前已就同一件事件發布重大訊息日期: 不適用\r\n30.其他敘明事項:\r\n無"},
{"出表日期":"1150122","發言日期":"1150121","發言時間":"171631","公司代號":"5215","公司名稱":"科嘉-KY","主旨 ":"代子公司蘇州嘉吉/科德/嘉財/艾普來/百宏/嘉皇/嘉駿 \r\n公告一年內累積處分同一有價證券達實收資本額20%","符合條款":"第20款","事實發生日":"1150121","說明":"1.證券名稱:\r\n上海證券交易所一天期國債逆回購GC001，代碼204001\r\n2.交易日期:115/1/21~115/1/21\r\n3.董事會通過日期: 不適用\r\n4.其他核決日期:\r\n核決層級:董事長核決\r\n民國115年01月21日\r\n5.交易數量、每單位價格及交易總金額:\r\n艾普來：124,230單位，均價：1.575%，\r\n百宏：84,550單位，均價：1.570%，\r\n嘉財：1,237,630單位，均價：1.585%，\r\n嘉皇：114,450單位，均價：1.585%\r\n嘉吉：113,150單位，均價：1.590%\r\n科德：587,950單位，均價：1.585%，\r\n嘉駿：408,970單位，均價：1.580%，\r\n總金額：267,105仟元，(約新台幣1,194,385千元)\r\n6.處分利益（或損失）（取得有價證券者不適用）:\r\n處份利益人民幣11仟元\r\n7.與交易標的公司之關係:\r\n非關係人\r\n8.迄目前為止，累積持有本交易證券（含本次交易）之數量、金額、持股\r\n比例及權利受限情形（如質押情形）:\r\n蘇州艾普來 無\r\n蘇州百宏 無\r\n蘇州嘉財電子 無\r\n蘇州嘉皇電子 無\r\n蘇州嘉吉電子 無\r\n蘇州科德 無\r\n重慶嘉駿 無\r\n質押情形：無\r\n9.迄目前為止，依「公開發行公司取得或處分資產處理準則」第三條所列之有價證券投\r\n資（含本次交易）占公司最近期財務報表中總資產及歸屬於母公司業主之權益之比例\r\n暨最近期財務報表中營運資金數額:\r\n總資產之比例：26.98%\r\n占股東權益之比例：35.03%\r\n營運資金：新台幣2,218,109仟元\r\n10.取得或處分之具體目的:\r\n投資理財\r\n11.本次交易表示異議董事之意見:\r\n無\r\n12.本次交易為關係人交易:\r\n否\r\n13.交易相對人及其與公司之關係:\r\n不適用\r\n14.監察人承認或審計委員會同意日期:\r\n不適用\r\n15.前已就同一件事件發布重大訊息日期: 不適用\r\n16.其他敘明事項:\r\n無"},
{"出表日期":"1150122","發言日期":"1150121","發言時間":"171648","公司代號":"5215","公司名稱":"科嘉-KY","主旨 ":"代子公司蘇州嘉吉/科德/嘉財/艾普來/百宏/嘉皇/嘉駿 \r\n公告一年內累積取得同一有價證券達實收資本額20%","符合條款":"第20款","事實發生日":"1150121","說明":"1.證券名稱:\r\n上海證券交易所一天期國債逆回購GC001，代碼204001\r\n2.交易日期:115/1/21~115/1/21\r\n3.董事會通過日期: 不適用\r\n4.其他核決日期:\r\n核決層級:董事長核決\r\n民國115年01月21日\r\n5.交易數量、每單位價格及交易總金額:\r\n艾普來：124,240單位，均價：1.565%，\r\n百宏：84,560單位，均價：1.565%，\r\n嘉財：1,237,680單位，均價：1.565%，\r\n嘉皇：114,450單位，均價：1.565%\r\n嘉吉：113,150單位，均價：1.565%\r\n科德：587,970單位，均價：1.565%，\r\n嘉駿：421,980單位，均價：1.565%，\r\n總金額：268,403仟元，(約新台幣1,200,191千元)\r\n6.處分利益（或損失）（取得有價證券者不適用）:\r\n不適用\r\n7.與交易標的公司之關係:\r\n非關係人\r\n8.迄目前為止，累積持有本交易證券（含本次交易）之數量、金額、持股\r\n比例及權利受限情形（如質押情形）:\r\n艾普來：124,240單位，均價：1.565%，\r\n百宏：84,560單位，均價：1.565%，\r\n嘉財：1,237,680單位，均價：1.565%，\r\n嘉皇：114,450單位，均價：1.565%\r\n嘉吉：113,150單位，均價：1.565%\r\n科德：587,970單位，均價：1.565%，\r\n嘉駿：421,980單位，均價：1.565%，\r\n質押情形：無\r\n9.迄目前為止，依「公開發行公司取得或處分資產處理準則」第三條所列之有價證券投\r\n資（含本次交易）占公司最近期財務報表中總資產及歸屬於母公司業主之權益之比例\r\n暨最近期財務報表中營運資金數額:\r\n總資產之比例：27.11%\r\n占股東權益之比例：35.20%\r\n營運資金：新台幣2,218,109仟元\r\n10.取得或處分之具體目的:\r\n投資理財\r\n11.本次交易表示異議董事之意見:\r\n無\r\n12.本次交易為關係人交易:\r\n否\r\n13.交易相對人及其與公司之關係:\r\n不適用\r\n14.監察人承認或審計委員會同意日期:\r\n不適用\r\n15.前已就同一件事件發布重大訊息日期: 不適用\r\n16.其他敘明事項:\r\n無"},
{"出表日期":"1150122","發言日期":"1150121","發言時間":"172010","公司代號":"3055","公司名稱":"蔚華科","主旨 ":"依公開發行公司資金貸與及背書保證處理準則第二十二條第一項\r\n第二及第三款規定公告資金貸與他人事項","符合條款":"第23款","事實發生日":"1150121","說明":"1.事實發生日:115/01/21\r\n2.接受資金貸與之:\r\n(1)公司名稱:蔚華電子科技（上海）有限公司\r\n(2)與資金貸與他人公司之關係:\r\n本公司間接投資持有100%之子公司。\r\n(3)資金貸與之限額(仟元):468,916\r\n(4)原資金貸與之餘額(仟元):0\r\n(5)本次新增資金貸與之金額(仟元):224,800\r\n(6)是否為董事會授權董事長對同一貸與對象分次撥貸或循環動用之資金貸與:是\r\n(7)迄事實發生日止資金貸與餘額(仟元):224,800\r\n(8)本次新增資金貸與之原因:\r\n短期營運週轉、償還境外關聯方借款及償還境內銀行短期借款需求。\r\n3.接受資金貸與公司所提供擔保品之:\r\n(1)內容:\r\n無\r\n(2)價值(仟元):0\r\n4.接受資金貸與公司最近期財務報表之:\r\n(1)資本(仟元):205,065\r\n(2)累積盈虧金額(仟元):-59,938\r\n5.計息方式:\r\n年利率 3.35%\r\n6.還款之:\r\n(1)條件:\r\n依合約規定，利息併同本金於還款時清償。\r\n(2)日期:\r\n借款期間自初次撥貸日起算一年。\r\n7.迄事實發生日為止，資金貸與餘額(仟元):\r\n224,800\r\n8.迄事實發生日為止，資金貸與餘額占公開發行公司最近期財務報表淨值之比率:\r\n12.79\r\n9.公司貸與他人資金之來源:\r\n子公司本身、母公司\r\n10.其他應敘明事項:\r\n本次異動有如下公司資金貸與本公司間接投資持有100%之子公司\r\n蔚華電子科技(上海)有限公司合計人民幣5,000萬元：\r\n(1)本公司貸與金額人民幣3,000萬元。\r\n(2)本公司之子公司欣傳投資股份有限公司貸與金額人民幣2,000萬元。"},
{"出表日期":"1150122","發言日期":"1150121","發言時間":"172037","公司代號":"2485","公司名稱":"兆赫","主旨 ":"代子公司ZINWELL HOLDING（SAMOA）CORPORATION\r\n公告董事會決議辦理現金減資案","符合條款":"第11款","事實發生日":"1150121","說明":"1.董事會決議日期:115/01/21\n2.減資緣由:現金減資退還股款\n3.減資金額:美金3,100,000元\n4.消除股份:3,100,000股\n5.減資比率:8.05%\n6.減資後股本:美金35,400,000元\n7.預定股東會日期:不適用\n8.預計減資新股上市後之上市普通股股數:不適用\n9.預計減資新股上市後之上市普通股股數占已發行普通股比率\n（減資後上市普通股股數/減資後已發行普通股股數）:不適用\n10.前二項預計減資後上巿普通股股數未達6000萬股且未達25%者，\n請說明股權流通性偏低之因應措施:不適用\n11.減資基準日:授權董事長訂定\n12.其他應敘明事項:無"},
{"出表日期":"1150122","發言日期":"1150121","發言時間":"172117","公司代號":"2485","公司名稱":"兆赫","主旨 ":"（更新公告）公告本公司涉及美國專利侵權訴訟案件之和解情形","符合條款":"第51款","事實發生日":"1150121","說明":"1.事實發生日:115/01/21\n2.公司名稱:兆赫電子股份有限公司\n3.與公司關係(請輸入本公司或子公司):本公司\n4.相互持股比例:不適用\n5.發生緣由:\n本公司前於114/11/03公告接獲 ContentNexus LLC 於美國德克薩斯州東區聯邦\n地方法院對本公司提起專利侵權訴訟。本公司與原告現已就前述訴訟達成和解，\n並已共同向法院提出相關文件，法院並已准予暫停訴訟程序，待雙方依程序完成撤案。\n6.因應措施:無\n7.其他應敘明事項(若事件發生或決議之主體係屬公開發行以上公司，本則重大訊息同時\n  符合證券交易法施行細則第7條第9款所定對股東權益或證券價格有重大影響之事項):無"},
{"出表日期":"1150122","發言日期":"1150121","發言時間":"172635","公司代號":"8411","公司名稱":"福貞-KY","主旨 ":"(更正背書保證之總限額)代子公司福建福貞金屬包裝有限公司公告\r\n新增背書保證金額達處理準則第二十五條第一項第三、四款規定\r\n辦理公告相關事宜","符合條款":"第22款","事實發生日":"1141229","說明":"1.事實發生日:114/12/29\r\n2.被背書保證之:\r\n(1)公司名稱:山東福貞金屬包裝有限公司\r\n(2)與提供背書保證公司之關係:\r\n100%關聯公司\r\n(3)背書保證之限額(仟元):7,568,343\r\n(4)原背書保證之餘額(仟元):628,180\r\n(5)本次新增背書保證之金額(仟元):269,220\r\n(6)迄事實發生日止背書保證餘額(仟元):897,400\r\n(7)被背書保證公司實際動支金額(仟元):508,692\r\n(8)本次新增背書保證之原因:\r\n因應公司營運規劃需求及充實資金來源。\r\n(1)公司名稱:河南福貞金屬包裝有限公司\r\n(2)與提供背書保證公司之關係:\r\n子公司\r\n(3)背書保證之限額(仟元):7,568,343\r\n(4)原背書保證之餘額(仟元):538,440\r\n(5)本次新增背書保證之金額(仟元):224,350\r\n(6)迄事實發生日止背書保證餘額(仟元):762,790\r\n(7)被背書保證公司實際動支金額(仟元):358,755\r\n(8)本次新增背書保證之原因:\r\n因應公司營運規劃需求及充實資金來源。\r\n(1)公司名稱:陝西福貞金屬包裝有限公司\r\n(2)與提供背書保證公司之關係:\r\n子公司\r\n(3)背書保證之限額(仟元):7,568,343\r\n(4)原背書保證之餘額(仟元):1,032,010\r\n(5)本次新增背書保證之金額(仟元):426,265\r\n(6)迄事實發生日止背書保證餘額(仟元):1,458,275\r\n(7)被背書保證公司實際動支金額(仟元):816,817\r\n(8)本次新增背書保證之原因:\r\n因應營運資金規劃及改善財務結構需求\r\n3.被背書保證公司提供擔保品之:\r\n(1)內容:\r\n陝西福貞公司不動產抵押\r\n(2)價值(仟元):475,507\r\n4.被背書保證公司最近期財務報表之:\r\n(1)資本(仟元):2,979,410\r\n(2)累積盈虧金額(仟元):145,881\r\n5.解除背書保證責任之:\r\n(1)條件:\r\n銀行授信合約屆期或借款償還額度終止\r\n(2)日期:\r\n銀行授信合約屆期或借款償還額度終止\r\n6.背書保證之總限額(仟元):\r\n8,264,530\r\n7.迄事實發生日為止，背書保證餘額(仟元):\r\n7,705,041\r\n8.迄事實發生日為止，A提供背書保證餘額占公開發行公司最近期財務報表淨值之\r\n比率:\r\n139.85\r\n9.迄事實發生日為止，背書保證、長期投資及資金貸與餘額合計數達該公開發行公\r\n司最近期財務報表淨值之比率:\r\n126.64\r\n10.其他應敘明事項:\r\n無"},
{"出表日期":"1150122","發言日期":"1150121","發言時間":"172655","公司代號":"1590","公司名稱":"亞德客-KY","主旨 ":"公告本公司受邀參加大和國泰證券(股)公司舉辦之法人說明會","符合條款":"第12款","事實發生日":"1150305","說明":"符合條款第四條第XX款：12\r\n事實發生日：115/03/05\r\n1.召開法人說明會之日期：115/03/05 ~ 115/03/06\r\n2.召開法人說明會之時間：10 時 00 分 \r\n3.召開法人說明會之地點：東京\r\n4.法人說明會擇要訊息：公司簡介與營運狀況說明\r\n5.其他應敘明事項：受邀參加大和國泰證券舉辦之法說會「Investment Conference 2026」。\r\n完整財務業務資訊請至公開資訊觀測站之法人說明會一覽表或法說會項目下查閱。"},
{"出表日期":"1150122","發言日期":"1150121","發言時間":"172723","公司代號":"1590","公司名稱":"亞德客-KY","主旨 ":"公告本公司受邀參加花旗環球證券股份有限公司舉辦之法人說明會","符合條款":"第12款","事實發生日":"1150309","說明":"符合條款第四條第XX款：12\r\n事實發生日：115/03/09\r\n1.召開法人說明會之日期：115/03/09\r\n2.召開法人說明會之時間：13 時 00 分 \r\n3.召開法人說明會之地點：台北遠東香格里拉\r\n4.法人說明會擇要訊息：公司簡介與營運狀況說明\r\n5.其他應敘明事項：受邀參加花旗環球證券舉辦之法說會「2026 March Corporate Day」。\r\n完整財務業務資訊請至公開資訊觀測站之法人說明會一覽表或法說會項目下查閱。"},
{"出表日期":"1150122","發言日期":"1150121","發言時間":"172753","公司代號":"1590","公司名稱":"亞德客-KY","主旨 ":"公告本公司受邀參加摩根大通證券股份有限公司舉辦之法人說明會","符合條款":"第12款","事實發生日":"1150311","說明":"符合條款第四條第XX款：12\r\n事實發生日：115/03/11\r\n1.召開法人說明會之日期：115/03/11 ~ 115/03/12\r\n2.召開法人說明會之時間：09 時 00 分 \r\n3.召開法人說明會之地點：台北君悅酒店\r\n4.法人說明會擇要訊息：公司簡介與營運狀況說明\r\n5.其他應敘明事項：受邀參加摩根大通證券舉辦之法說會「Taiwan CEO-CFO」。\r\n完整財務業務資訊請至公開資訊觀測站之法人說明會一覽表或法說會項目下查閱。"},
{"出表日期":"1150122","發言日期":"1150121","發言時間":"172824","公司代號":"1590","公司名稱":"亞德客-KY","主旨 ":"公告本公司受邀參加香港美銀證券舉辦之法人說明會","符合條款":"第12款","事實發生日":"1150317","說明":"符合條款第四條第XX款：12\r\n事實發生日：115/03/17\r\n1.召開法人說明會之日期：115/03/17\r\n2.召開法人說明會之時間：09 時 00 分 \r\n3.召開法人說明會之地點：台北君悅酒店\r\n4.法人說明會擇要訊息：公司簡介與營運狀況說明\r\n5.其他應敘明事項：受邀參加香港美銀證券舉辦之法說會「2026 Asia Tech Conference」。\r\n完整財務業務資訊請至公開資訊觀測站之法人說明會一覽表或法說會項目下查閱。"},
{"出表日期":"1150122","發言日期":"1150121","發言時間":"172846","公司代號":"4764","公司名稱":"雙鍵","主旨 ":"公告本公司獨立董事異動","符合條款":"第6款","事實發生日":"1150121","說明":"1.發生變動日期:115/01/21\n2.選任或變動人員別（請輸入法人董事、法人監察人、獨立董事、自然人董事\n  或自然人監察人）:獨立董事\n3.舊任者職稱及姓名:朱富春\n4.舊任者簡歷:雙鍵化工股份有限公司獨立董事\n5.新任者職稱及姓名:不適用\n6.新任者簡歷:不適用\n7.異動情形（請輸入「辭職」、「解任」、「任期屆滿」、「逝世」或「新任」）:逝世\n8.異動原因:逝世\n9.新任者選任時持股數:不適用\n10.原任期（例xx/xx/xx ~ xx/xx/xx）:112/06/28-115/06/27\n11.新任生效日期:不適用\n12.同任期董事變動比率:1/7\n13.同任期獨立董事變動比率:1/3\n14.同任期監察人變動比率:不適用\n15.屬三分之一以上董事發生變動（請輸入是或否）:否\n16.其他應敘明事項(若事件發生或決議之主體係屬公開發行以上公司，本則重大訊息同時\n   符合證券交易法施行細則第7條第6款所定對股東權益或證券價格有重大影響之事項):\n本公司於115/01/21接獲獨立董事朱富春先生逝世之通知。"},
{"出表日期":"1150122","發言日期":"1150121","發言時間":"172902","公司代號":"4764","公司名稱":"雙鍵","主旨 ":"公告本公司審計委員會及薪資報酬委員會委員異動","符合條款":"第6款","事實發生日":"1150121","說明":"1.發生變動日期:115/01/21\n2.功能性委員會名稱:審計委員會及薪資報酬委員會\n3.舊任者姓名:朱富春\n4.舊任者簡歷:雙鍵化工股份有限公司獨立董事\n5.新任者姓名:不適用\n6.新任者簡歷:不適用\n7.異動情形（請輸入「辭職」、「解任」、「任期屆滿」、「逝世」或「新任」）:逝世\n8.異動原因:逝世\n9.原任期（例xx/xx/xx ~ xx/xx/xx）:112/06/28-115/06/27\n10.新任生效日期:不適用\n11.其他應敘明事項:\n本公司於115/01/21接獲審計委員會及薪資報酬委員會委員朱富春先生逝世之通知。"},
{"出表日期":"1150122","發言日期":"1150121","發言時間":"173620","公司代號":"2474","公司名稱":"可成","主旨 ":"公告本公司買回股份金額達新台幣三億元以上","符合條款":"第35款","事實發生日":"1150121","說明":"1.本次買回股份數量累積達公司已發行股份總額百分之二或金額達新台幣三億元以上之日期:115/01/21\r\n2.本次買回股份數量(股):750,000\r\n3.本次買回股份總金額(元):153,281,168\r\n4.本次平均每股買回價格(元):204.37\r\n5.於買回期間內累積已持有自己公司股份數量(股):20,952,000\r\n6.於買回期間內累積已持有自己公司股份數量占公司已發行股份總數之比率(%):3.54\r\n7.其他應敘明事項:\r\n無"},
{"出表日期":"1150122","發言日期":"1150121","發言時間":"174329","公司代號":"5876","公司名稱":"上海商銀","主旨 ":"代子公司上海商業銀行有限公司公告擬辦理物業翻新","符合條款":"第51款","事實發生日":"1150121","說明":"1.事實發生日:115/01/21\n2.公司名稱:上海商業銀行　\n3.與公司關係(請輸入本公司或子公司):子公司\n4.相互持股比例:57.6%\n5.發生緣由:香港九龍旺角彌敦道666號的物業翻新工程承攬契約\n6.因應措施:不適用\n7.其他應敘明事項(若事件發生或決議之主體係屬公開發行以上公司，本則重大訊息同時\n  符合證券交易法施行細則第7條第9款所定對股東權益或證券價格有重大影響之事項):\n預計契約總金額不超過港幣188,162,654元(約新台幣762,118,020元(含稅)，契約起迄自\n2026年02月27日起至2027年06月27日。此安排於2026年1月21日董事會通過授權行政會議\n決定工程承包商及最終合同金額。"},
{"出表日期":"1150122","發言日期":"1150121","發言時間":"174400","公司代號":"5876","公司名稱":"上海商銀","主旨 ":"代子公司上海商業銀行有限公司公告第75屆股東周年大會\r\n召集事由(補充114/08/20公告)","符合條款":"第17款","事實發生日":"1150121","說明":"1.董事會決議日期:115/01/21\n2.股東會召開日期:115/04/22\n3.股東會召開地點:香港中環皇后大道中12號上海商業銀行大廈\n4.召集事由一、報告事項:無\n5.召集事由二、承認事項:(1)審閱截至114年12月31日止年度經審核之財務報表及董事會\n與核數師報告書。(2)宣派114年度股息（如有）。\n6.召集事由三、討論事項:(1)通過截至114年12月31日止年度之董事袍金。(2)重新委聘核\n數師及授權董事會釐定其酬金。(3)採納The Policy on the Acquisition and Disposal\nof Assets。\n7.召集事由四、選舉事項:重選董事\n8.召集事由五、其他議案:無\n9.召集事由六、臨時動議:無\n10.停止過戶起始日期:115/04/15\n11.停止過戶截止日期:115/04/22\n12.其他應敘明事項:無"},
{"出表日期":"1150122","發言日期":"1150121","發言時間":"174615","公司代號":"8454","公司名稱":"富邦媒","主旨 ":"公告本公司董事會決議召開115年股東常會相關事宜\n(召開方式：視訊輔助股東會)","符合條款":"第17款","事實發生日":"1150121","說明":"1.董事會決議日期：115/01/21\r\n2.股東會召開日期：115/05/27\r\n3.股東會召開地點：台北市信義區菸廠路88號(臺北文創大樓)6樓多功能廳\r\n4.股東會召開方式(實體股東會/視訊輔助股東會/視訊股東會)：視訊輔助股東會\r\n5.召集事由一：報告事項\r\n(1)：本公司114年度營業報告。\r\n(2)：審計委員會報告。\r\n(3)：本公司114年度關係人交易情形報告。\r\n(4)：本公司114年度員工及董事酬勞分派情形報告。\r\n6.召集事由二：承認事項\r\n(1)：本公司114年度營業報告書及財務報表案。\r\n(2)：本公司114年度盈餘分配案。\r\n7.召集事由三：討論及選舉事項\r\n(1)：本公司董事(含獨立董事)全面改選案。\r\n8.召集事由四：討論及選舉事項\r\n(1)：解除本公司第九屆董事競業限制案。\r\n9.臨時動議：\r\n10.停止過戶起始日期：115/03/29\r\n11.停止過戶截止日期：115/05/27\r\n12.其他應敘明事項：(1)有關本公司盈餘分派內容，預計於股東常會四十日前經董事會決議後另行公告。\n(2)依公司法第172-1條及第192-1條規定，自115年03月20日至115年03月30日止\n受理股東提案及董事候選人提名，受理處所：富邦媒體科技股份有限公司財會處\n(地址：台北市內湖區洲子街96號4樓)。"},
{"出表日期":"1150122","發言日期":"1150121","發言時間":"174640","公司代號":"3702","公司名稱":"大聯大","主旨 ":"代本公司100%持股之子公司-共創智能(股)公司及\r\n世友投資(股)公司公告董事會通過營業分割讓與案\r\n(補充114/10/28公告)","符合條款":"第11款","事實發生日":"1150121","說明":"1.併購種類(如合併、分割、收購或股份受讓):\r\n分割\r\n2.事實發生日:115/1/21\r\n3.參與併購公司名稱(如合併另一方公司、分割新設公司、收購或受讓股份標的公司之\r\n名稱:\r\n分割公司：世友投資(股)公司(下稱「世友公司」）\r\n受讓分割公司：共創智能(股)公司(下稱「共創公司」)\r\n4.交易相對人(如合併另一方公司、分割讓與他公司、收購或受讓股份之交易對象):\r\n受讓分割公司：共創智能(股)公司\r\n受讓股份公司：大聯大控股(股)公司(下稱「本公司」)\r\n5.交易相對人為關係人:是\r\n6.交易相對人與公司之關係(本公司轉投資持股達XX%之被投資公司)，並說明選定\r\n收購、受讓他公司股份之對象為關係企業或關係人之原因及是否不影響股東權益:\r\n世友公司及共創公司為本公司百分之百持股之子公司，為落實集團專業分工，茲進行集團\r\n物流轉投資業務調整，選定共創公司為本分割案之交易相對人。\r\n因係內部調整，故對本公司每股淨值及每股盈餘無影響。\r\n7.併購目的及條件，包括併購理由、對價條件及支付時點:\r\n為落實集團專業分工\r\n8.併購後預計產生之效益:\r\n提高競爭力及市場占有率\r\n9.併購對每股淨值及每股盈餘之影響:\r\n為落實集團專業分工，故對本公司每股淨值及每股盈餘無影響\r\n10.併購之對價種類及資金來源:\r\n世友公司之物流轉投資業務之營業價值換共創公司普通股，共創公司發行普通股予本公司\r\n11.換股比例及其計算依據:\r\n(1)換股比例: 按世友公司之物流轉投資業務營業價值每51.17元換共創公司普通股1股，\r\n由共創公司發行普通股20,663仟股(每股面額新台幣10元)予本公司。\r\n(2)計算依據: 參考世友公司之物流轉投資業務營業價值、共創公司每股淨值，以及獨立\r\n專家出具之營業價值及分割換股比例合理性意見書而訂定。\r\n12.本次交易會計師、律師或證券承銷商出具非合理性意見:否\r\n13.會計師或律師事務所名稱或證券承銷商公司名稱:\r\n國富浩華聯合會計師事務所\r\n14.會計師或律師姓名:\r\n邱繼盛\r\n15.會計師或律師開業證書字號:\r\n金管證審字第10200032833號\r\n16.獨立專家就本次併購換股比例、配發股東之現金或其他財產之合理性意見書內容\r\n(一、包含公開收購價格訂定所採用之方法、原則或計算方式及與國際慣用之市價法\r\n、成本法及現金流量折現法之比較。二、被收購公司與已上市櫃同業之財務狀況\r\n、獲利情形及本益比之比較情形。三、公開收購價格若參考鑑價機構之鑑價報告者\r\n，應說明該鑑價報告內容及結論。四、收購人融資償還計畫若係以被收購公司或合\r\n併後存續公司之資產或股份為擔保者，應說明對被收購公司或合併後存續公司財務\r\n業務健全性之影響評估):\r\n本案為落實集團專業分工，世友公司以物流轉投資業務之營業價值進行分割暨減資，同時\r\n共創公司按物流轉投資業務之營業價值發行普通股予本公司，以取得世友公司物流轉投資\r\n業務，尚屬合理。\r\n17.預定完成日程:\r\n分割基準日為民國115年1月21日\r\n18.既存或新設公司承受消滅(或分割)公司權利義務相關事項(註二):\r\n除物流轉投資業務相關營業所生之債務與世友公司於分割前之債務係屬可分者外，共創公\r\n司應就分割前世友公司所負債務於其受讓營業之出資範圍，依企業併購法規定與世友公司\r\n負連帶清償責任。但債權人之連帶清償責任請求權，自分割基準日起二年內不行使而消滅\r\n，自分割基準日起，世友公司物流轉投資業務相關營業之資產、負債暨截至分割基準日仍\r\n存在之相關權利義務，均由共創公司依法概括承受。\r\n19.參與合併公司之基本資料(註三):\r\n不適用\r\n20.分割之相關事項(含預定讓與既存公司或新設公司之營業、資產之評價價值；被\r\n分割公司或其股東所取得股份之總數、種類及數量；被分割公司資本減少時，其資\r\n本減少有關事項)(註：若非分割公告時，則不適用):\r\n(1)分割讓與之營業、資產之評價價值：分割基準日之營業價值為1,057,262仟元。\r\n(2)被分割公司或其股東所取得股份之總數、種類及數量：共創公司發行普通股\r\n20,663仟股(每股面額新台幣10元)予本公司。\r\n(3)被分割公司資本減少時，其資本減少有關事項：世友公司於分割基準日辦理\r\n減資新台幣1,033,148仟元，銷除股份103,315仟股。\r\n21.併購股份未來移轉之條件及限制:\r\n無\r\n22.併購完成後之計畫(包含一、繼續經營公司業務之意願及計畫內容。二、是否發生\r\n解散、下市(櫃)、重大變更組織、資本、業務計畫、財務及生產、對公司重要人員\r\n、資產之安排或運用，或其他任何影響公司股東權益之重大事項):\r\n不適用\r\n23.其他重要約定事項:\r\n無\r\n24.其他與併購相關之重大事項:\r\n不適用\r\n25.本次交易，董事有無異議:否\r\n26.併購交易中涉及利害關係董事資訊(自然人董事姓名或法人董事名稱暨其代表人姓名\r\n、其自身或其代表之法人有利害關係之重要內容(包括但不限於實際或預計投資其他\r\n參加併購公司之方式、持股比率、交易價格、是否參與併購公司之經營及其他投資條件\r\n等情形)、其應迴避或不迴避理由、迴避情形、贊成或反對併購決議之理由):\r\n無\r\n27.是否涉及營運模式變更:否\r\n28.營運模式變更說明(註四):\r\n不適用\r\n29.過去一年及預計未來一年內與交易相對人交易情形(註五):\r\n不適用\r\n30.資金來源(註五):\r\n不適用\r\n31.其他敘明事項(註六):\r\n無\r\n註二、既存或新設公司承受消滅公司權利義務相關事項，包括庫藏股及已發行具有股權性質有\r\n　　　價證券之處理原則。\r\n註三：參與合併公司之基本資料包括公司名稱及所營業務之主要內容。\r\n註四：倘涉營運模式變更，請於欄位敘明包括營業範圍變更、產品線擴充/縮減、製程調整、產業\r\n　　　水平/垂直整合，或其他涉及營運架構調整事項。\r\n註五：非屬私募資金用以併購案件者，得填寫不適用。\r\n註六：若本案成就前，尚需經國內、外主管機關(如:投審會、公平交易委員會、反壟斷局或其他單位)核准或許可者，應予敘明相關事項。"},
{"出表日期":"1150122","發言日期":"1150121","發言時間":"174720","公司代號":"3702","公司名稱":"大聯大","主旨 ":"公告本公司取得100%轉投資子公司共創智能(股)公司普通股(補充114/10/28公告)","符合條款":"第20款","事實發生日":"1150121","說明":"1.標的物之名稱及性質（屬特別股者，並應標明特別股約定發行條件，如股息率等）:\r\n共創智能(股)公司普通股\r\n2.事實發生日:115/1/21~115/1/21\r\n3.董事會通過日期: 民國114年10月28日\r\n4.其他核決日期: 不適用\r\n5.交易數量、每單位價格及交易總金額:\r\n交易單位數量: 20,663仟股\n每單位價格:每股新台幣51.17元\n交易總金額:新台幣1,057,262仟元\r\n6.交易相對人及其與公司之關係（交易相對人如屬自然人，且非公司之\r\n關係人者，得免揭露其姓名）:\r\n(1)交易相對人：共創智能(股)公司；\n(2)與公司之關係：持股100%之子公司\r\n7.交易相對人為關係人者，並應公告選定關係人為交易對象之原因及前次移\r\n轉之所有人、前次移轉之所有人與公司及交易相對人間相互之關係、前次\r\n移轉日期及移轉金額:\r\n選定關係人為交易對象之原因：為落實集團專業分工，本公司100%持股之子公司世友\n投資(股)公司將該公司獨立營運之物流轉投資業務分割轉讓予本公司另一100%持股\n之子公司共創智能(股)公司，並由共創智能(股)公司發行普通股予本公司作為受讓該\n營業之對價。\n前次移轉之所有人、前次移轉之所有人與公司及交易相對人間相互之關係、前次移轉\n日期及移轉金額：不適用。\r\n8.交易標的最近五年內所有權人曾為公司之關係人者，尚應公告關係人之取\r\n得及處分日期、價格及交易當時與公司之關係:\r\n不適用\r\n9.本次係處分債權之相關事項（含處分之債權附隨擔保品種類、處分債權\r\n如有屬對關係人債權者尚需公告關係人名稱及本次處分該關係人之債權\r\n帳面金額:\r\n不適用\r\n10.處分利益（或損失）（取得有價證券者不適用）（原遞延者應列表說明\r\n認列情形）:\r\n不適用\r\n11.交付或付款條件（含付款期間及金額）、契約限制條款及其他重要約定\r\n事項:\r\n無\r\n12.本次交易之決定方式、價格決定之參考依據及決策單位:\r\n交易之決定方式：本公司董事會決議\n價格決定之參考依據：獨立專家會計師合理性意見書\n決策單位：董事會\r\n13.取得或處分有價證券標的公司每股淨值:\r\n10.08元\r\n14.迄目前為止，累積持有本交易證券（含本次交易）之數量、金額、持股\r\n比例及權利受限情形（如質押情形）:\r\n累積持有本交易證券之數量：普通股86,663仟股\n累積持有本交易證券之金額：新台幣1,797,024仟元\n持股比率：100%\n權利受限情形：無\r\n15.迄目前為止，依「公開發行公司取得或處分資產處理準則」第三條所列\r\n之有價證券投資（含本次交易）占公司最近期財務報表中總資產及歸屬\r\n於母公司業主之權益之比例暨最近期財務報表中營運資金數額（註二）:\r\n(1)占公司最近期財務報表中總資產比例：92.05%\n(2)占公司最近期財務報表中歸屬於母公司業主之權益之比例：139.03%\n(3)最近期財務報表中營運資金數額：新台幣-13,320,123仟元\n(4)取得有價證券之資金來源及具體原因：共創智能 (股)公司發行普通股予本公司作\n為受讓世友投資(股)公司分割獨立營運之物流轉投資業務相關營業及世友投資(股)公\n司分割減資之對價\r\n16.經紀人及經紀費用:\r\n無\r\n17.取得或處分之具體目的或用途:\r\n為落實集團專業分工\r\n18.本次交易表示異議董事之意見:\r\n無\r\n19.本次交易為關係人交易:是\r\n20.監察人承認或審計委員會同意日期:\r\n民國114年10月28日\r\n21.本次交易會計師出具非合理性意見:否\r\n22.會計師事務所名稱:\r\n國富浩華聯合會計師事務所\r\n23.會計師姓名:\r\n邱繼盛\r\n24.會計師開業證書字號:\r\n金管證審字第10200032833號\r\n25.是否涉及營運模式變更:否\r\n26.營運模式變更說明:\r\n\r\n27.過去一年及預計未來一年內與交易相對人交易情形:\r\n不適用\r\n28.資金來源:\r\n不適用\r\n29.前已就同一件事件發布重大訊息日期:\r\n114年10月28日\r\n30.其他敘明事項:\r\n無"},
{"出表日期":"1150122","發言日期":"1150121","發言時間":"175932","公司代號":"4958","公司名稱":"臻鼎-KY","主旨 ":"代子公司鵬鼎控股(深圳)股份有限公司公告董事會通過各項議案","符合條款":"第51款","事實發生日":"1150121","說明":"1.事實發生日:115/01/21\n2.公司名稱:鵬鼎控股(深圳)股份有限公司\n3.與公司關係(請輸入本公司或子公司):子公司\n4.相互持股比例:72.24%\n5.發生緣由:\n代子公司公告董事會通過各項議案：\n(1)關於預計公司2026年度日常關聯交易的議案。\n(2)關於申請2026年金融衍生品交易額度的議案。\n(3)關於申請銀行授信額度的議案。\n(4)關於申請向控股子公司提供借款額度的議案。\n6.因應措施:依規定代子公司於公開資訊觀測站公告。\n7.其他應敘明事項(若事件發生或決議之主體係屬公開發行以上公司，本則重大訊息同時\n  符合證券交易法施行細則第7條第9款所定對股東權益或證券價格有重大影響之事項):\n 無。"},
{"出表日期":"1150122","發言日期":"1150121","發言時間":"175956","公司代號":"2323","公司名稱":"中環","主旨 ":"公告本公司處分有價證券","符合條款":"第20款","事實發生日":"1150121","說明":"1.證券名稱:\r\n華星光 普通股\r\n2.交易日期:115/1/9~115/1/21\r\n3.董事會通過日期: 不適用\r\n4.其他核決日期:\r\n核決層級:董事長核決\r\n民國115年01月21日\r\n5.交易數量、每單位價格及交易總金額:\r\n交易數量(仟股):1,510\r\n每單位價格(元):290.29\r\n交易總金額(元):438,337,450\r\n6.處分利益（或損失）（取得有價證券者不適用）:\r\n處分損失 2,955,946元\r\n7.與交易標的公司之關係:\r\n無\r\n8.迄目前為止，累積持有本交易證券（含本次交易）之數量、金額、持股\r\n比例及權利受限情形（如質押情形）:\r\n持有餘額:1,363,000股、金額:401,276,195元 \r\n持股比例:0.97%、權利受限情形:無\r\n9.迄目前為止，依「公開發行公司取得或處分資產處理準則」第三條所列之有價證券投\r\n資（含本次交易）占公司最近期財務報表中總資產及歸屬於母公司業主之權益之比例\r\n暨最近期財務報表中營運資金數額:\r\n占總資產比例:81.74%             \r\n占歸屬於母公司業主之權益比例:114.78%           \r\n營運資金數額:7,442,300仟元\r\n10.取得或處分之具體目的:\r\n投資組合\r\n11.本次交易表示異議董事之意見:\r\n無\r\n12.本次交易為關係人交易:\r\n否\r\n13.交易相對人及其與公司之關係:\r\n不適用\r\n14.監察人承認或審計委員會同意日期:\r\n不適用\r\n15.前已就同一件事件發布重大訊息日期: 不適用\r\n16.其他敘明事項:\r\n已於114/12/31授權有權交易人在115年第一季期間，得於集中交易市場進行有價證券交易"},
{"出表日期":"1150122","發言日期":"1150121","發言時間":"180029","公司代號":"2323","公司名稱":"中環","主旨 ":"公告本公司取得有價證券","符合條款":"第20款","事實發生日":"1150121","說明":"1.證券名稱:\r\n華星光 普通股\r\n2.交易日期:115/1/13~115/1/21\r\n3.董事會通過日期: 不適用\r\n4.其他核決日期:\r\n核決層級:董事長核決\r\n民國115年01月21日\r\n5.交易數量、每單位價格及交易總金額:\r\n交易數量(仟股):1,100\r\n每單位價格(元):276.59\r\n交易總金額(元):304,252,698\r\n6.處分利益（或損失）（取得有價證券者不適用）:\r\n不適用\r\n7.與交易標的公司之關係:\r\n無\r\n8.迄目前為止，累積持有本交易證券（含本次交易）之數量、金額、持股\r\n比例及權利受限情形（如質押情形）:\r\n持有餘額:1,363,000股、金額:401,276,195元 \r\n持股比例:0.97%、權利受限情形:無\r\n9.迄目前為止，依「公開發行公司取得或處分資產處理準則」第三條所列之有價證券投\r\n資（含本次交易）占公司最近期財務報表中總資產及歸屬於母公司業主之權益之比例\r\n暨最近期財務報表中營運資金數額:\r\n占總資產比例:81.74%             \r\n占歸屬於母公司業主之權益比例:114.78%           \r\n營運資金數額:7,442,300仟元\r\n10.取得或處分之具體目的:\r\n投資組合\r\n11.本次交易表示異議董事之意見:\r\n無\r\n12.本次交易為關係人交易:\r\n否\r\n13.交易相對人及其與公司之關係:\r\n不適用\r\n14.監察人承認或審計委員會同意日期:\r\n不適用\r\n15.前已就同一件事件發布重大訊息日期: 不適用\r\n16.其他敘明事項:\r\n已於114/12/31授權有權交易人在115年第一季期間，得於集中交易市場進行有價證券交易"},
{"出表日期":"1150122","發言日期":"1150121","發言時間":"180106","公司代號":"2323","公司名稱":"中環","主旨 ":"公告本公司取得有價證券","符合條款":"第20款","事實發生日":"1150121","說明":"1.證券名稱:\r\n國巨 普通股\r\n2.交易日期:114/12/17~115/1/21\r\n3.董事會通過日期: 不適用\r\n4.其他核決日期:\r\n核決層級:董事長核決\r\n民國115年01月21日\r\n5.交易數量、每單位價格及交易總金額:\r\n交易數量(仟股):1,320\r\n每單位價格(元):253.05\r\n交易總金額(元):334,024,491\r\n6.處分利益（或損失）（取得有價證券者不適用）:\r\n不適用\r\n7.與交易標的公司之關係:\r\n無\r\n8.迄目前為止，累積持有本交易證券（含本次交易）之數量、金額、持股\r\n比例及權利受限情形（如質押情形）:\r\n持有餘額:340,000股、金額:96,529,725元\r\n持股比例:0.016%、權利受限情形: 無\r\n9.迄目前為止，依「公開發行公司取得或處分資產處理準則」第三條所列之有價證券投\r\n資（含本次交易）占公司最近期財務報表中總資產及歸屬於母公司業主之權益之比例\r\n暨最近期財務報表中營運資金數額:\r\n占總資產比例:81.74%             \r\n占歸屬於母公司業主之權益比例:114.78%           \r\n營運資金數額:7,442,300仟元\r\n10.取得或處分之具體目的:\r\n投資組合\r\n11.本次交易表示異議董事之意見:\r\n無\r\n12.本次交易為關係人交易:\r\n否\r\n13.交易相對人及其與公司之關係:\r\n不適用\r\n14.監察人承認或審計委員會同意日期:\r\n不適用\r\n15.前已就同一件事件發布重大訊息日期: 不適用\r\n16.其他敘明事項:\r\n已於114/12/31授權有權交易人在115年第一季期間，得於集中交易市場進行有價證券交易"},
{"出表日期":"1150122","發言日期":"1150121","發言時間":"180126","公司代號":"4958","公司名稱":"臻鼎-KY","主旨 ":"代子公司鵬鼎控股(深圳)股份有限公司公告通過資金貸與額度案","符合條款":"第23款","事實發生日":"1150121","說明":"1.事實發生日:115/01/21\r\n2.接受資金貸與之:\r\n(1)公司名稱:慶鼎精密電子(淮安)有限公司\r\n(2)與資金貸與他人公司之關係:\r\n關聯企業\r\n(3)資金貸與之限額(仟元):58,255,866\r\n(4)原資金貸與之餘額(仟元):4,458,800\r\n(5)本次新增資金貸與之金額(仟元):4,458,800\r\n(6)是否為董事會授權董事長對同一貸與對象分次撥貸或循環動用之資金貸與:是\r\n(7)迄事實發生日止資金貸與餘額(仟元):8,917,600\r\n(8)本次新增資金貸與之原因:\r\n董事會通過2026年度資金貸與額度\r\n3.接受資金貸與公司所提供擔保品之:\r\n(1)內容:\r\n無\r\n(2)價值(仟元):0\r\n4.接受資金貸與公司最近期財務報表之:\r\n(1)資本(仟元):15,166,707\r\n(2)累積盈虧金額(仟元):23,546,424\r\n5.計息方式:\r\n按合約規定\r\n6.還款之:\r\n(1)條件:\r\n按合約規定\r\n(2)日期:\r\n按合約規定\r\n7.迄事實發生日為止，資金貸與餘額(仟元):\r\n8,917,600\r\n8.迄事實發生日為止，資金貸與餘額占公開發行公司最近期財務報表淨值之比率:\r\n7.89\r\n9.公司貸與他人資金之來源:\r\n子公司本身\r\n10.其他應敘明事項:\r\n(1)董事會通過2026年短期資金貸與額度CNY10億元。\r\n(2)折算匯率: CNY/TWD 4.4588。"},
{"出表日期":"1150122","發言日期":"1150121","發言時間":"180157","公司代號":"4958","公司名稱":"臻鼎-KY","主旨 ":"代子公司鵬鼎控股(深圳)股份有限公司公告通過資金貸與額度案","符合條款":"第23款","事實發生日":"1150121","說明":"1.事實發生日:115/01/21\r\n2.接受資金貸與之:\r\n(1)公司名稱:宏恒勝電子科技(淮安)有限公司\r\n(2)與資金貸與他人公司之關係:\r\n關聯企業\r\n(3)資金貸與之限額(仟元):58,255,866\r\n(4)原資金貸與之餘額(仟元):8,917,600\r\n(5)本次新增資金貸與之金額(仟元):8,917,600\r\n(6)是否為董事會授權董事長對同一貸與對象分次撥貸或循環動用之資金貸與:是\r\n(7)迄事實發生日止資金貸與餘額(仟元):17,835,200\r\n(8)本次新增資金貸與之原因:\r\n董事會通過2026年度資金貸與額度\r\n3.接受資金貸與公司所提供擔保品之:\r\n(1)內容:\r\n無\r\n(2)價值(仟元):0\r\n4.接受資金貸與公司最近期財務報表之:\r\n(1)資本(仟元):6,360,421\r\n(2)累積盈虧金額(仟元):-3,346,121\r\n5.計息方式:\r\n按合約規定\r\n6.還款之:\r\n(1)條件:\r\n按合約規定\r\n(2)日期:\r\n按合約規定\r\n7.迄事實發生日為止，資金貸與餘額(仟元):\r\n17,835,200\r\n8.迄事實發生日為止，資金貸與餘額占公開發行公司最近期財務報表淨值之比率:\r\n15.79\r\n9.公司貸與他人資金之來源:\r\n子公司本身\r\n10.其他應敘明事項:\r\n(1)董事會通過2026年短期資金貸與額度CNY20億元。\r\n(2)折算匯率: CNY/TWD 4.4588。"},
{"出表日期":"1150122","發言日期":"1150121","發言時間":"180201","公司代號":"2323","公司名稱":"中環","主旨 ":"公告本公司取得有價證券","符合條款":"第20款","事實發生日":"1150121","說明":"1.證券名稱:\r\n群聯 普通股\r\n2.交易日期:114/12/31~115/1/21\r\n3.董事會通過日期: 不適用\r\n4.其他核決日期:\r\n核決層級:董事長核決\r\n民國115年01月21日\r\n5.交易數量、每單位價格及交易總金額:\r\n交易數量(仟股):188\r\n每單位價格(元):1,750.74\r\n交易總金額(元):329,138,730\r\n6.處分利益（或損失）（取得有價證券者不適用）:\r\n不適用\r\n7.與交易標的公司之關係:\r\n無\r\n8.迄目前為止，累積持有本交易證券（含本次交易）之數量、金額、持股\r\n比例及權利受限情形（如質押情形）:\r\n持有餘額:100,000股、金額:194,649,857元    \r\n持股比例:0.05%、權利受限情形: 無\r\n9.迄目前為止，依「公開發行公司取得或處分資產處理準則」第三條所列之有價證券投\r\n資（含本次交易）占公司最近期財務報表中總資產及歸屬於母公司業主之權益之比例\r\n暨最近期財務報表中營運資金數額:\r\n占總資產比例:81.74%\r\n占歸屬於母公司業主之權益比例:114.78% \r\n營運資金數額:7,442,300仟元\r\n10.取得或處分之具體目的:\r\n投資組合\r\n11.本次交易表示異議董事之意見:\r\n無\r\n12.本次交易為關係人交易:\r\n否\r\n13.交易相對人及其與公司之關係:\r\n不適用\r\n14.監察人承認或審計委員會同意日期:\r\n不適用\r\n15.前已就同一件事件發布重大訊息日期: 不適用\r\n16.其他敘明事項:\r\n已於114/12/31授權有權交易人在115年第一季期間，得於集中交易市場進行有價證券交易"},
{"出表日期":"1150122","發言日期":"1150121","發言時間":"180206","公司代號":"3712","公司名稱":"永崴投控","主旨 ":"代子公司勁永科技鹽城有限公司公告股東決議事項","符合條款":"第18款","事實發生日":"1150121","說明":"1.股東臨時會日期:115/01/21\n2.重要決議事項:修訂本公司「公司章程」部分條文案\n3.其他應敘明事項:無"},
{"出表日期":"1150122","發言日期":"1150121","發言時間":"180221","公司代號":"3712","公司名稱":"永崴投控","主旨 ":"代子公司勁永科技鹽城有限公司公告單一法人股東重新指派\r\n董事","符合條款":"第6款","事實發生日":"1150121","說明":"1.發生變動日期:115/01/21\n2.選任或變動人員別（請輸入法人董事、法人監察人、獨立董事、自然人董事\n  或自然人監察人）:法人董事、法人監察人\n3.舊任者職稱及姓名:\n董事:\n(1)勁永國際股份(香港)有限公司:劉素芳\n(2)勁永國際股份(香港)有限公司:林坤煌\n(3)勁永國際股份(香港)有限公司:王美珠\n監察人:\n(1)勁永國際股份(香港)有限公司:卜慶藩\n4.舊任者簡歷:\n劉素芳:勁永科技鹽城有限公司董事\n林坤煌:勁永科技鹽城有限公司董事\n王美珠:勁永科技鹽城有限公司董事\n卜慶藩:勁永科技鹽城有限公司監察人\n5.新任者職稱及姓名:勁永國際股份(香港)有限公司:劉素芳\n6.新任者簡歷:勁永科技鹽城有限公司董事\n7.異動情形（請輸入「辭職」、「解任」、「任期屆滿」、「逝世」或「新任」）:\n新任\n8.異動原因:改派\n9.新任者選任時持股數:不適用\n10.原任期（例xx/xx/xx ~ xx/xx/xx）:不適用\n11.新任生效日期:115/01/21\n12.同任期董事變動比率:不適用\n13.同任期獨立董事變動比率:不適用\n14.同任期監察人變動比率:不適用\n15.屬三分之一以上董事發生變動（請輸入是或否）:是\n16.其他應敘明事項(若事件發生或決議之主體係屬公開發行以上公司，本則重大訊息同時\n   符合證券交易法施行細則第7條第6款所定對股東權益或證券價格有重大影響之事項):\n修改章程,董事改為一人,不設監察人。"},
{"出表日期":"1150122","發言日期":"1150121","發言時間":"180226","公司代號":"4958","公司名稱":"臻鼎-KY","主旨 ":"代子公司鵬鼎控股(深圳)股份有限公司公告通過資金貸與額度案","符合條款":"第23款","事實發生日":"1150121","說明":"1.事實發生日:115/01/21\r\n2.接受資金貸與之:\r\n(1)公司名稱:奎盛科技(深圳)有限公司\r\n(2)與資金貸與他人公司之關係:\r\n關聯企業\r\n(3)資金貸與之限額(仟元):58,255,866\r\n(4)原資金貸與之餘額(仟元):133,764\r\n(5)本次新增資金貸與之金額(仟元):133,764\r\n(6)是否為董事會授權董事長對同一貸與對象分次撥貸或循環動用之資金貸與:是\r\n(7)迄事實發生日止資金貸與餘額(仟元):267,528\r\n(8)本次新增資金貸與之原因:\r\n董事會通過2026年度資金貸與額度\r\n3.接受資金貸與公司所提供擔保品之:\r\n(1)內容:\r\n無\r\n(2)價值(仟元):0\r\n4.接受資金貸與公司最近期財務報表之:\r\n(1)資本(仟元):89,176\r\n(2)累積盈虧金額(仟元):129,586\r\n5.計息方式:\r\n按合約規定\r\n6.還款之:\r\n(1)條件:\r\n按合約規定\r\n(2)日期:\r\n按合約規定\r\n7.迄事實發生日為止，資金貸與餘額(仟元):\r\n267,528\r\n8.迄事實發生日為止，資金貸與餘額占公開發行公司最近期財務報表淨值之比率:\r\n0.24\r\n9.公司貸與他人資金之來源:\r\n子公司本身\r\n10.其他應敘明事項:\r\n(1)董事會通過2026年短期資金貸與額度CNY3,000萬元。\r\n(2)折算匯率: CNY/TWD 4.4588。"},
{"出表日期":"1150122","發言日期":"1150121","發言時間":"180255","公司代號":"4958","公司名稱":"臻鼎-KY","主旨 ":"代子公司宏啟勝精密電子(秦皇島)有限公司公告\r\n通過資金貸與額度案","符合條款":"第23款","事實發生日":"1150121","說明":"1.事實發生日:115/01/21\r\n2.接受資金貸與之:\r\n(1)公司名稱:慶鼎精密電子(淮安)有限公司\r\n(2)與資金貸與他人公司之關係:\r\n關聯企業\r\n(3)資金貸與之限額(仟元):146,917,721\r\n(4)原資金貸與之餘額(仟元):2,229,400\r\n(5)本次新增資金貸與之金額(仟元):2,229,400\r\n(6)是否為董事會授權董事長對同一貸與對象分次撥貸或循環動用之資金貸與:是\r\n(7)迄事實發生日止資金貸與餘額(仟元):4,458,800\r\n(8)本次新增資金貸與之原因:\r\n董事會通過2026年度資金貸與額度\r\n3.接受資金貸與公司所提供擔保品之:\r\n(1)內容:\r\n無\r\n(2)價值(仟元):0\r\n4.接受資金貸與公司最近期財務報表之:\r\n(1)資本(仟元):15,166,707\r\n(2)累積盈虧金額(仟元):23,546,424\r\n5.計息方式:\r\n按合約規定\r\n6.還款之:\r\n(1)條件:\r\n按合約規定\r\n(2)日期:\r\n按合約規定\r\n7.迄事實發生日為止，資金貸與餘額(仟元):\r\n4,458,800\r\n8.迄事實發生日為止，資金貸與餘額占公開發行公司最近期財務報表淨值之比率:\r\n3.95\r\n9.公司貸與他人資金之來源:\r\n子公司本身\r\n10.其他應敘明事項:\r\n(1)董事會通過2026年短期資金貸與額度CNY5億元。\r\n(2)折算匯率:CNY/TWD 4.4588。"},
{"出表日期":"1150122","發言日期":"1150121","發言時間":"180313","公司代號":"6431","公司名稱":"光麗-KY","主旨 ":"更正本公司114年12月定期公告財務資訊申報金額","符合條款":"第51款","事實發生日":"1150121","說明":"1.事實發生日:115/01/21\n2.公司名稱:光麗生技控股股份有限公司\n3.與公司關係(請輸入本公司或子公司):本公司\n4.相互持股比例:不適用\n5.發生緣由:本公司更正114年12月份透過其他綜合損益按公允價值衡量之金融資產\n-流動金額\n6.更正資訊項目/報表名稱:定期公告財務資訊\n7.更正前金額/內容/頁次:\n透過其他綜合損益按公允價值衡量之金融資產-流動:3,000仟元\n8.更正後金額/內容/頁次:\n透過其他綜合損益按公允價值衡量之金融資產-流動:0仟元\n9.因應措施:於公開資訊觀測站發佈重大訊息並重新公告\n10.其他應敘明事項:無"},
{"出表日期":"1150122","發言日期":"1150121","發言時間":"180325","公司代號":"4958","公司名稱":"臻鼎-KY","主旨 ":"代子公司宏啟勝精密電子(秦皇島)有限公司公告\r\n通過資金貸與額度案","符合條款":"第23款","事實發生日":"1150121","說明":"1.事實發生日:115/01/21\r\n2.接受資金貸與之:\r\n(1)公司名稱:宏恒勝電子科技(淮安)有限公司\r\n(2)與資金貸與他人公司之關係:\r\n關聯企業\r\n(3)資金貸與之限額(仟元):146,917,721\r\n(4)原資金貸與之餘額(仟元):2,229,400\r\n(5)本次新增資金貸與之金額(仟元):2,229,400\r\n(6)是否為董事會授權董事長對同一貸與對象分次撥貸或循環動用之資金貸與:是\r\n(7)迄事實發生日止資金貸與餘額(仟元):4,458,800\r\n(8)本次新增資金貸與之原因:\r\n董事會通過2026年度資金貸與額度\r\n3.接受資金貸與公司所提供擔保品之:\r\n(1)內容:\r\n無\r\n(2)價值(仟元):0\r\n4.接受資金貸與公司最近期財務報表之:\r\n(1)資本(仟元):6,360,421\r\n(2)累積盈虧金額(仟元):-3,346,121\r\n5.計息方式:\r\n按合約規定\r\n6.還款之:\r\n(1)條件:\r\n按合約規定\r\n(2)日期:\r\n按合約規定\r\n7.迄事實發生日為止，資金貸與餘額(仟元):\r\n4,458,800\r\n8.迄事實發生日為止，資金貸與餘額占公開發行公司最近期財務報表淨值之比率:\r\n3.95\r\n9.公司貸與他人資金之來源:\r\n子公司本身\r\n10.其他應敘明事項:\r\n(1)董事會通過2026年短期資金貸與額度CNY5億元。\r\n(2)折算匯率:CNY/TWD 4.4588。"},
{"出表日期":"1150122","發言日期":"1150121","發言時間":"180357","公司代號":"4958","公司名稱":"臻鼎-KY","主旨 ":"代子公司鵬鼎國際有限公司公告通過資金貸與額度案","符合條款":"第23款","事實發生日":"1150121","說明":"1.事實發生日:115/01/21\r\n2.接受資金貸與之:\r\n(1)公司名稱:鵬鼎科技股份有限公司\r\n(2)與資金貸與他人公司之關係:\r\n關聯企業\r\n(3)資金貸與之限額(仟元):2,509,124\r\n(4)原資金貸與之餘額(仟元):1,254,680\r\n(5)本次新增資金貸與之金額(仟元):1,254,680\r\n(6)是否為董事會授權董事長對同一貸與對象分次撥貸或循環動用之資金貸與:是\r\n(7)迄事實發生日止資金貸與餘額(仟元):2,509,360\r\n(8)本次新增資金貸與之原因:\r\n董事會通過2026年度資金貸與額度\r\n3.接受資金貸與公司所提供擔保品之:\r\n(1)內容:\r\n無\r\n(2)價值(仟元):0\r\n4.接受資金貸與公司最近期財務報表之:\r\n(1)資本(仟元):4,525,000\r\n(2)累積盈虧金額(仟元):-2,079,233\r\n5.計息方式:\r\n按合約規定\r\n6.還款之:\r\n(1)條件:\r\n按合約規定\r\n(2)日期:\r\n按合約規定\r\n7.迄事實發生日為止，資金貸與餘額(仟元):\r\n2,509,360\r\n8.迄事實發生日為止，資金貸與餘額占公開發行公司最近期財務報表淨值之比率:\r\n2.22\r\n9.公司貸與他人資金之來源:\r\n子公司本身\r\n10.其他應敘明事項:\r\n(1)董事會通過2026年短期資金貸與額度USD4,000萬元。\r\n(2)本次新增金額為2026年資金貸與額度總額,致資金貸與\r\n餘額重覆計算原2025年資金貸與額度及本次金額。\r\n(3)折算匯率: USD/TWD 31.3670。"},
{"出表日期":"1150122","發言日期":"1150121","發言時間":"180426","公司代號":"4958","公司名稱":"臻鼎-KY","主旨 ":"代子公司鵬鼎國際有限公司公告通過資金貸與額度註銷案","符合條款":"第23款","事實發生日":"1150121","說明":"1.事實發生日:115/01/21\r\n2.接受資金貸與之:\r\n(1)公司名稱:Peng Shen Technology (Thailand) Co.,Ltd.\r\n(2)與資金貸與他人公司之關係:\r\n關聯企業\r\n(3)資金貸與之限額(仟元):2,509,124\r\n(4)原資金貸與之餘額(仟元):501,872\r\n(5)本次新增資金貸與之金額(仟元):0\r\n(6)是否為董事會授權董事長對同一貸與對象分次撥貸或循環動用之資金貸與:是\r\n(7)迄事實發生日止資金貸與餘額(仟元):501,872\r\n(8)本次新增資金貸與之原因:\r\n董事會通過2026年度資金貸與額度註銷\r\n3.接受資金貸與公司所提供擔保品之:\r\n(1)內容:\r\n無\r\n(2)價值(仟元):0\r\n4.接受資金貸與公司最近期財務報表之:\r\n(1)資本(仟元):2,480,250\r\n(2)累積盈虧金額(仟元):-732,675\r\n5.計息方式:\r\n按合約規定\r\n6.還款之:\r\n(1)條件:\r\n按合約規定\r\n(2)日期:\r\n按合約規定\r\n7.迄事實發生日為止，資金貸與餘額(仟元):\r\n501,872\r\n8.迄事實發生日為止，資金貸與餘額占公開發行公司最近期財務報表淨值之比率:\r\n0.44\r\n9.公司貸與他人資金之來源:\r\n子公司本身\r\n10.其他應敘明事項:\r\n(1)董事會通過2026年資金貸與額度註銷。\r\n(2)折算匯率:THB/TWD 0.9921。"},
{"出表日期":"1150122","發言日期":"1150121","發言時間":"180539","公司代號":"8454","公司名稱":"富邦媒","主旨 ":"本公司董事會通過115年度本公司及子公司多項資本支出計劃","符合條款":"第51款","事實發生日":"1150121","說明":"1.事實發生日:115/01/21\n2.公司名稱:富邦媒體科技股份有限公司\n3.與公司關係(請輸入本公司或子公司):本公司\n4.相互持股比例:不適用\n5.發生緣由:不適用\n6.因應措施:不適用\n7.其他應敘明事項(若事件發生或決議之主體係屬公開發行以上公司，本則重大訊息同時\n  符合證券交易法施行細則第7條第9款所定對股東權益或證券價格有重大影響之事項):\n  本公司今日召開董事會，會中核准115年度本公司及子公司多項資本支出計劃，\n  包括物流中心建置、倉儲營運設備、資訊設備及配送車隊建置等，經費合計\n  約新台幣10.3億元。上述資本支出計劃款項之支付，係依實際執行進度請款。"},
{"出表日期":"1150122","發言日期":"1150121","發言時間":"181212","公司代號":"2515","公司名稱":"中工","主旨 ":"代孫公司超場共創股份有限公司公告取消使用權資產","符合條款":"第20款","事實發生日":"1150121","說明":"1.標的物之名稱及性質（如坐落台中市北區ＸＸ段ＸＸ小段土地）:\r\n台北市松山區東興路12號2樓\r\n2.事實發生日:115/1/21~115/1/21\r\n3.董事會通過日期: 民國115年1月21日\r\n4.其他核決日期: 不適用\r\n5.交易單位數量（如ＸＸ平方公尺，折合ＸＸ坪）、每單位價格及交易總金額:\r\n交易單位數量：辦公室：1坪\n每單位價格：2,095元/坪(未稅)\n交易總金額：2,095元/月(未稅)\n本案取消承租\r\n6.交易相對人及其與公司之關係（交易相對人如屬自然人，且非公司之關\r\n係人者，得免揭露其姓名）:\r\n鴻益建設股份有限公司/關係人\r\n7.交易相對人為關係人者，並應公告選定關係人為交易對象之原因及前次移轉之\r\n所有人、前次移轉之所有人與公司及交易相對人間相互之關係、前次移轉日期\r\n及移轉金額:\r\n(1)選定關係人為交易對象之原因：集團管理及整體規劃，租賃為辦公場所使用。\n(2)所有人、前次移轉之所有人與公司及交易相對人間相互之關係、前次移轉日期\n及移轉金額：不適用。\r\n8.交易標的最近五年內所有權人曾為公司之關係人者，尚應公告關係\r\n人之取得及處分日期、價格及交易當時與公司之關係:\r\n不適用。\r\n9.預計處分利益（或損失）（取得資產者不適用）（遞延者應列表說明\r\n認列情形）:\r\n不適用。\r\n10.交付或付款條件（含付款期間及金額）、契約限制條款及其他重要約定\r\n事項:\r\n一、租金交付條款\n(1)每月新台幣2,095(未稅)，契約總金額為NT$25,140(未稅)。\n(2)租賃期間：租賃期間為一年，自民國115年1月1日起至民國115年12月31日止。\n(3)以一季為一期給付。\n 二、其他重要約定事項:無。\n本案取消承租\r\n11.本次交易之決定方式（如招標、比價或議價）、價格決定之參考依據及\r\n決策單位:\r\n市場行情。\r\n12.專業估價者事務所或公司名稱及其估價金額:\r\n不適用。\r\n13.專業估價師姓名:\r\n不適用。\r\n14.專業估價師開業證書字號:\r\n不適用。\r\n15.估價報告是否為限定價格、特定價格或特殊價格:否或不適用\r\n16.是否尚未取得估價報告:否或不適用\r\n17.尚未取得估價報告之原因:\r\n不適用\r\n18.估價結果有重大差異時，其差異原因及會計師意見:\r\n不適用。\r\n19.會計師事務所名稱:\r\n不適用。\r\n20.會計師姓名:\r\n不適用。\r\n21.會計師開業證書字號:\r\n不適用。\r\n22.經紀人及經紀費用:\r\n不適用。\r\n23.取得或處分之具體目的或用途:\r\n作為辦公場所使用。\r\n24.本次交易表示異議之董事之意見:\r\n不適用。\r\n25.本次交易為關係人交易:是\r\n26.監察人承認或審計委員會同意日期:\r\n不適用\r\n27.本次交易係向關係人取得不動產或其使用權資產:是\r\n28.依「公開發行公司取得或處分資產處理準則」第十六條規定\r\n評估之價格:不適用\r\n29.依前項評估之價格較交易價格為低者，依同準則第十七條規\r\n定評估之價格:不適用\r\n30.前已就同一件事件發布重大訊息日期: 不適用\r\n31.其他敘明事項:\r\n因公司營運調整，已無向鴻益建設(股)公司承租辦公室之需求，故取消承租。"},
{"出表日期":"1150122","發言日期":"1150121","發言時間":"182619","公司代號":"8454","公司名稱":"富邦媒","主旨 ":"公告本公司董事會決議與富邦人壽保險股份有限公司取得二筆使用權資產","符合條款":"第20款","事實發生日":"1150121","說明":"1.標的物之名稱及性質（如坐落台中市北區ＸＸ段ＸＸ小段土地）:\r\n一、台北市內湖區瑞光路4*0號9樓(含地下第三層車位4個)\n二、台北市內湖區瑞光路4*0號地下第三層車位1個\r\n2.事實發生日:115/1/21~115/1/21\r\n3.董事會通過日期: 民國115年1月21日\r\n4.其他核決日期: 不適用\r\n5.交易單位數量（如ＸＸ平方公尺，折合ＸＸ坪）、每單位價格及交易總金額:\r\n一、續租9樓(含地下第三層免租車位4個)\n(一)交易單位數量：434.6坪\n(二)每單位價格：\n1.租期：115/04/01~118/03/31\n  每單位價格：新台幣約1,536元/坪/月(未稅)\n  租金金額：新台幣667,449元/月(未稅)\n2.租期：118/04/01~120/03/31\n  每單位價格：新台幣約1,582元/坪/月(未稅)\n  租金金額：新台幣687,472元/月(未稅)\n(三)使用權資產金額：新台幣38,886,774元\n\n二、增租地下第三層車位1個： \n(一)交易單位數量：1個\n(二)每單位價格：新台幣3,600元/月(未稅)\n(三)使用權資產金額：新台幣206,380元\r\n6.交易相對人及其與公司之關係（交易相對人如屬自然人，且非公司之關\r\n係人者，得免揭露其姓名）:\r\n(1)交易相對人：富邦人壽保險股份有限公司\n(2)與公司之關係：其他關係人\r\n7.交易相對人為關係人者，並應公告選定關係人為交易對象之原因及前次移轉之\r\n所有人、前次移轉之所有人與公司及交易相對人間相互之關係、前次移轉日期\r\n及移轉金額:\r\n(1)選定關係人為交易對象之原因：地點及使用坪數較符合本公司人員使用需求，適逢\n物件出租人為關係人。\n(2)前次移轉所有人：華邦電子股份有限公司\n(3)前次移轉之所有人與公司之關係：非關係人\n(4)前次移轉之所有人與交易相對人之關係：非關係人\n(5)前次移轉日期：民國95年09月14日(依買賣契約書所載)\n(6)前次移轉面積：\n土地：3,609.04平方公尺，折合1,091.73坪(依買賣契約書所載)\n建物：24,840.62平方公尺，折合7,514.27坪(依買賣契約書所載)\n(7)前次移轉金額：共計新台幣1,888,000,000元(含稅，依買賣契約書所載)\r\n8.交易標的最近五年內所有權人曾為公司之關係人者，尚應公告關係\r\n人之取得及處分日期、價格及交易當時與公司之關係:\r\n(1)交易標的最近五年內所有權人：富邦人壽保險股份有限公司\n(2)取得日期：民國95年09月14日(依買賣契約書所載)\n(3)取得面積：\n土地：3,609.04平方公尺，折合1,091.73坪(依買賣契約書所載)\n建物：24,840.62平方公尺，折合7,514.27坪(依買賣契約書所載)\n(4)取得金額：共計新台幣1,888,000,000元(含稅，依買賣契約書所載)\n(5)交易當時與公司之關係：富邦金控持股100%之子公司(富邦金控係本公司之\n最終母公司)\r\n9.預計處分利益（或損失）（取得資產者不適用）（遞延者應列表說明\r\n認列情形）:\r\n不適用\r\n10.交付或付款條件（含付款期間及金額）、契約限制條款及其他重要約定\r\n事項:\r\n(1)交付或付款條件：月繳\n(2)租期：115/04/01~120/03/31\n(3)契約限制條款：無\n(4)其他重要約定事項：無\r\n11.本次交易之決定方式（如招標、比價或議價）、價格決定之參考依據及\r\n決策單位:\r\n董事會授權董事長依內部管理辦法議定\r\n12.專業估價者事務所或公司名稱及其估價金額:\r\n不適用\r\n13.專業估價師姓名:\r\n不適用\r\n14.專業估價師開業證書字號:\r\n不適用\r\n15.估價報告是否為限定價格、特定價格或特殊價格:否或不適用\r\n16.是否尚未取得估價報告:否或不適用\r\n17.尚未取得估價報告之原因:\r\n不適用\r\n18.估價結果有重大差異時，其差異原因及會計師意見:\r\n不適用\r\n19.會計師事務所名稱:\r\n不適用\r\n20.會計師姓名:\r\n不適用\r\n21.會計師開業證書字號:\r\n不適用\r\n22.經紀人及經紀費用:\r\n無\r\n23.取得或處分之具體目的或用途:\r\n維持現有辦公室空間，並符合車輛停放需求。\r\n24.本次交易表示異議之董事之意見:\r\n無\r\n25.本次交易為關係人交易:是\r\n26.監察人承認或審計委員會同意日期:\r\n民國115年01月20日\r\n27.本次交易係向關係人取得不動產或其使用權資產:是\r\n28.依「公開發行公司取得或處分資產處理準則」第十六條規定\r\n評估之價格:不適用\r\n29.依前項評估之價格較交易價格為低者，依同準則第十七條規\r\n定評估之價格:不適用\r\n30.前已就同一件事件發布重大訊息日期: 不適用\r\n31.其他敘明事項:\r\n無"},
{"出表日期":"1150122","發言日期":"1150121","發言時間":"185012","公司代號":"2062","公司名稱":"橋椿","主旨 ":"公告本公司董事會決議召開股東常會","符合條款":"第17款","事實發生日":"1150121","說明":"1.董事會決議日期：115/01/21\r\n2.股東會召開日期：115/04/30\r\n3.股東會召開地點：台中市西屯區臺灣大道四段610號4樓(台中裕園花園酒店)\r\n4.股東會召開方式(實體股東會/視訊輔助股東會/視訊股東會)：實體股東會\r\n5.召集事由一：報告事項\r\n(1)：民國一一四年度營業狀況。\r\n(2)：審計委員會審查民國一一四年度決算表冊。\r\n(3)：民國一一四年度員工及董事酬勞分配情形。\r\n(4)：民國一一四年度盈餘分派情形。\r\n(5)：審計委員會與獨立董事成員及內部稽核主管之溝通情形。\r\n(6)：修訂【永續發展實務守則】部分條文。\r\n(7)：其他報告事項。\r\n6.召集事由二：承認事項\r\n(1)：民國一一四年度決算表冊（含合併財務報表及個體財務報表）案，提請 承認。\r\n(2)：民國一一四年度盈餘分配案，提請 承認。\r\n7.召集事由三：討論事項\r\n(1)：修訂【股東會議事規則】部分條文，提請 公決。\r\n8.臨時動議：\r\n9.停止過戶起始日期：115/03/02\r\n10.停止過戶截止日期：115/04/30\r\n11.其他應敘明事項：本次股東常會股東得以電子方式行使表決權。"},
{"出表日期":"1150122","發言日期":"1150121","發言時間":"191143","公司代號":"2301","公司名稱":"光寶科","主旨 ":"本公司董事會決議通過公開收購宇智網通股份有限公司普通股","符合條款":"第11款","事實發生日":"1150121","說明":"1.併購種類(如合併、分割、收購或股份受讓):\r\n收購\r\n2.事實發生日:115/1/21\r\n3.參與併購公司名稱(如合併另一方公司、分割新設公司、收購或受讓股份標的公司之\r\n名稱:\r\n宇智網通股份有限公司(以下簡稱「宇智公司」或「被收購\r\n公司」)\r\n4.交易相對人(如合併另一方公司、分割讓與他公司、收購或受讓股份之交易對象):\r\n宇智公司參與應賣股東\r\n5.交易相對人為關係人:否\r\n6.交易相對人與公司之關係(本公司轉投資持股達XX%之被投資公司)，並說明選定\r\n收購、受讓他公司股份之對象為關係企業或關係人之原因及是否不影響股東權益:\r\n本次收購採公開收購方式進行，倘有本公司關係人參與應賣，\r\n本公司依法不得拒絕或排除，故交易相對人可能為關係人，\r\n惟因公開收購價格與條件均屬一律，並不影響股東權益。\r\n7.併購目的及條件，包括併購理由、對價條件及支付時點:\r\n(1)公開收購之目的：\r\n本公司公開收購取得宇智公司普通股股份之目的：本公司本次以公開收\r\n購方式取得被收購公司普通股股份，係基於策略性投資目的，著眼雙方公\r\n司於既有網路通訊領域之客戶群及產品佈局優勢互補，擬與宇智公司儘早\r\n展開各項緊密的策略合作，藉由股權投資與產品技術開發、生產、銷售面\r\n的資源結合，共同擴大網通事業的版圖，在整體產業局勢發展及技術創新\r\n等面向即時掌握市場脈動、強化在 5G+ 未來世代網路之布局。\r\n(2)公開收購之對價：\r\n本次公開收購對價為每股現金新臺幣 54 元整。\r\n(3)預訂公開收購期間：\r\n自民國115年1月23日(下稱「收購期間開始日」)起\r\n至民國115年3月12日(下稱「收購期間屆滿日」)止。\r\n接受申請應賣時間為收購有價證券期間每個營業日\r\n上午9時00分至下午3時30分(臺灣時間)。\r\n惟公開收購人得依法向金融監督管理委員會申報並公告\r\n延長收購期間，但延長收購期間不得超過五十日，且以一次為限。\r\n每個營業日接受申請應賣時間及方式，請參閱公開收購說明書。\r\n(4)本次公開收購對價支付時點：\r\n在本次公開收購之條件成就下，公開收購對價將由受委任機構元大證券於\r\n公開收購期間屆滿日（如經延長則為延長期間屆滿日）次日起算五個營業日\r\n（含第五個營業日）以內，優先以銀行匯款方式支付至臺灣集中保管結算所\r\n提供予元大證券之應賣人銀行帳號，倘應賣人銀行帳號有誤或因其他原因致\r\n無法完成匯款時，以支票（抬頭劃線並禁止背書轉讓）掛號郵寄至臺灣集中\r\n保管結算所所提供之應賣人地址。匯款金額/支票金額之計算，係以應賣人\r\n成交股份收購對價扣除應賣人依法應繳納之證券交易稅、臺灣集中保管結算\r\n所及證券經紀商手續費、銀行匯款費用或掛號郵寄支票之郵資，及其他支付\r\n收購對價所必要之合理費用，並計算至「元」為止（不足一元之部分捨棄）。\r\n(5)其他公開收購條件請詳閱公開收購說明書。\r\n8.併購後預計產生之效益:\r\n本次公開收購除了可以認列合理的投資收益外，基於策略性\r\n投資目的，著眼雙方公司於既有網路通訊領域之客戶群及產\r\n品佈局優勢互補，擬與宇智公司儘早展開各項緊密的策略合\r\n作，藉由股權投資與產品技術開發、生產、銷售面的資源結\r\n合，共同擴大網通事業的版圖，在整體產業局勢發展及技術\r\n創新等面向即時掌握市場脈動、強化在5G+ 未來世代網路之\r\n布局。\r\n9.併購對每股淨值及每股盈餘之影響:\r\n公開收購完成後，透過認列合理之投資收益，對日後每股淨\r\n值與每股盈餘應有正面之助益。本公司將視最終收購結果，\r\n依相關法令規定或視實際需要評估是否與被收購公司進一步\r\n整併、使被收購公司成為本公司之全資子公司，因此後續不\r\n排除被收購公司將依櫃檯買賣中心之規定進行終止櫃檯買賣。\r\n屆時若有併購之具體計畫，將依相關法令規定辦理。如能發\r\n揮綜效，對日後每股淨值與每股盈餘應有正面之助益。\r\n10.併購之對價種類及資金來源:\r\n本次公開收購對價為每股現金新臺幣54元，所需現金對價總\r\n計為新臺幣2,035,481,400元，全數由本公司以自有資金支應。\r\n11.換股比例及其計算依據:\r\n一、換股比例：不適用。本次公開收購全數以現金為對價，\r\n收購價格為每股新臺幣54元。\r\n二、計算依據：不適用。\r\n12.本次交易會計師、律師或證券承銷商出具非合理性意見:否\r\n13.會計師或律師事務所名稱或證券承銷商公司名稱:\r\n立本台灣聯合會計師事務所\r\n14.會計師或律師姓名:\r\n張書成會計師\r\n15.會計師或律師開業證書字號:\r\n(86)台財證(六)第74537號\r\n16.獨立專家就本次併購換股比例、配發股東之現金或其他財產之合理性意見書內容\r\n(一、包含公開收購價格訂定所採用之方法、原則或計算方式及與國際慣用之市價法\r\n、成本法及現金流量折現法之比較。二、被收購公司與已上市櫃同業之財務狀況\r\n、獲利情形及本益比之比較情形。三、公開收購價格若參考鑑價機構之鑑價報告者\r\n，應說明該鑑價報告內容及結論。四、收購人融資償還計畫若係以被收購公司或合\r\n併後存續公司之資產或股份為擔保者，應說明對被收購公司或合併後存續公司財務\r\n業務健全性之影響評估):\r\n(一)本案經獨立專家考量被收購公司特性及各評價方法之\r\n評估限制並分析對本案之適當性，採用市場法-\r\n可類比公司法、市場法-可類比交易法及市價法作為評價方法，\r\n據以推算被收購公司普通股之理論價格，並推算其每股普通股\r\n合理收購價格區間。經本案獨立專家評估被收購公司普通股\r\n股票之公開收購價格合理區間為新臺幣50.75至60.84元。\r\n(二)被收購公司與已上市櫃同業之財務狀況、獲利情形及本\r\n益比之比較情形：被收購公司與已上市櫃同業之財務狀況、\r\n獲利情形及本益比之比較情形請詳閱公開收購說明書之附件\r\n二-獨立專家對收購對價現金價格計算之評價合理性意見書。\r\n(三)公開收購價格若參考鑑價機構之鑑價報告者，應說明該\r\n鑑價報告內容及結論：不適用。\r\n(四)收購人融資償還計畫若係以被收購公司或合併後存續公\r\n司之資產或股份為擔保者，應說明對被收購公司或合併後存\r\n續公司財務業務健全性之影響評估：不適用。\r\n17.預定完成日程:\r\n本公開收購案依據法令規定必須向金融監督管理委員會申報\r\n並公告，公開收購期間預計自民國115年1月23日起至115年3月12\r\n日止。在本次公開收購之條件成就下，公開收購對價將由受\r\n委任機構元大證券於公開收購期間屆滿日（如經延長則為延\r\n長期間屆滿日）次日起算五個營業日（含第五個營業日）以\r\n內撥付。\r\n18.既存或新設公司承受消滅(或分割)公司權利義務相關事項(註二):\r\n不適用\r\n19.參與合併公司之基本資料(註三):\r\n不適用\r\n20.分割之相關事項(含預定讓與既存公司或新設公司之營業、資產之評價價值；被\r\n分割公司或其股東所取得股份之總數、種類及數量；被分割公司資本減少時，其資\r\n本減少有關事項)(註：若非分割公告時，則不適用):\r\n不適用\r\n21.併購股份未來移轉之條件及限制:\r\n無\r\n22.併購完成後之計畫(包含一、繼續經營公司業務之意願及計畫內容。二、是否發生\r\n解散、下市(櫃)、重大變更組織、資本、業務計畫、財務及生產、對公司重要人員\r\n、資產之安排或運用，或其他任何影響公司股東權益之重大事項):\r\n(1)繼續經營公司業務之意願及計畫內容\r\n本公司為台灣首家上市電子公司，以先進的光電半導體與電源管理實\r\n力，通過不斷地創新和研發，已經成為全球電子行業的領導者之一，產\r\n品涵蓋了各種電子元器件、LED 照明系統、矩陣 LED 顯示幕、汽車電子、\r\n智慧家居和物聯網等領域，近年積極佈局雲端運算電源、汽車電子、光\r\n電半導體、5G & AIoT，未來將以綠色資料中心、永續運輸、高效能基礎\r\n設施作為中長期發展的成長引擎。\r\n被收購公司深耕無線通訊技術領域，致力於產品創新研發，掌握軟體、\r\n硬體與韌體關鍵核心技術，以客戶為中心，針對不同的客戶需求，提供\r\n差異化全方位網路通訊解決方案，提供之產品解決方案涵蓋 5G NR, 4G\r\nLTE, Wi-Fi 7, Wi-Fi 6/6E 等，應用於企業、物聯網、智慧家庭及移動車\r\n載等用戶，並提供雲端軟硬體整合服務。\r\n本公司本次以公開收購方式取得被收購公司普通股股份，係基於策略性\r\n投資目的，著眼雙方公司於既有網路通訊領域之客戶群及產品佈局優勢\r\n互補，擬與宇智公司儘早展開各項緊密的策略合作，藉由股權投資與產\r\n品技術開發、生產、銷售面的資源結合，共同擴大網通事業的版圖，在\r\n整體產業局勢發展及技術創新等面向即時掌握市場脈動、強化在 5G+ 未\r\n來世代網路之布局。\r\n完成本次公開收購後，本公司原則上將使被收購公司繼續經營其現有業\r\n務。\r\n(2)是否發生解散、下市(櫃)、重大變更組織、資本、業務計畫、財務及生\r\n產，或其他任何影響公司股東權益之重大事項。\r\n於本公開收購說明書刊印之日，本次公開收購完成後本公司無使被收購公\r\n司產生下列情形之計畫：解散、變動組織、變動資本、變動業務計畫、變\r\n動財務狀況、變動生產。然而本公司不排除視實際情況建議被收購公司進\r\n行調整。\r\n本公司於本次公開收購完成後，並無立即促使被收購公司終止櫃檯買賣之\r\n具體計畫；惟依櫃檯買賣中心業務規則第 12 條之 2 第 1 項第 17 款規定，\r\n若被收購公司已成為本公司持股逾 70% 之子公司，櫃檯買賣中心得終止其\r\n有價證券櫃檯買賣，故本次公開收購完成後，本公司將視最終收購結果，依\r\n相關法令規定或視實際需要評估是否與被收購公司進一步整併、使被收購\r\n公司成為本公司之全資子公司，因此後續不排除被收購公司將依櫃檯買賣\r\n中心之規定進行終止櫃檯買賣。屆時若有併購之具體計畫，將依相關法令\r\n規定辦理。\r\n除公開收購說明書另有載明者外，於公開收購說明書刊印之日，就本公司\r\n目前所知及預期，並無其他影響被收購公司股東權益之重大事項。\r\n23.其他重要約定事項:\r\n無\r\n24.其他與併購相關之重大事項:\r\n(1)預定收購數量及最低收購數量：\r\n本次預定收購數量為37,694,100股（下稱「預定收購數量」），\r\n即被收購公司於經濟部商工登記公示資料查詢系統顯示民國114年7月4日\r\n最後異動日所載之已發行股份總數37,694,100股\r\n（下稱「已發行股份總數」）之100%；惟若最終有效應賣之數量未達\r\n預定收購數量，但已達7,538,820股\r\n（即被收購公司已發行股份總數之20%，下稱「最低收購數量」）時，\r\n則本公開收購之數量條件即告成就。\r\n在本次公開收購之條件成就\r\n（係指有效應賣股份&#63849;&#63870;已達最低收購&#63849;&#63870;時），\r\n且本次公開收購未依法停止進行之情況下，\r\n本公司將收購所有參加應賣之股份。\r\n為免應賣人所獲對價不足支付證券交易稅、\r\n臺灣集中保管結算所及證券經紀商手續費、\r\n銀行匯款費用或掛號郵寄支票之郵資及其他支付收購對價所必要之合理費用，\r\n應賣股&#63849;低於2股者恕不受理。\r\n(2)其餘注意事項請詳公開收購說明書。\r\n25.本次交易，董事有無異議:否\r\n26.併購交易中涉及利害關係董事資訊(自然人董事姓名或法人董事名稱暨其代表人姓名\r\n、其自身或其代表之法人有利害關係之重要內容(包括但不限於實際或預計投資其他\r\n參加併購公司之方式、持股比率、交易價格、是否參與併購公司之經營及其他投資條件\r\n等情形)、其應迴避或不迴避理由、迴避情形、贊成或反對併購決議之理由):\r\n無\r\n27.是否涉及營運模式變更:否\r\n28.營運模式變更說明(註四):\r\n不適用\r\n29.過去一年及預計未來一年內與交易相對人交易情形(註五):\r\n過去一年：無\r\n未來一年：本次公開收購完成後，本公司將視最終收購結果\r\n，依相關法令規定或視實際需要評估是否與被收購公司進一\r\n步整併、使被收購公司成為本公司之全資子公司，因此後續\r\n不排除被收購公司將依櫃檯買賣中心之規定進行終止櫃檯買\r\n賣。屆時若有併購之具體計畫，將依相關法令規定辦理，惟\r\n目前尚無具體計畫。\r\n30.資金來源(註五):\r\n本公司自有資金\r\n31.其他敘明事項(註六):\r\n一、為進行本公開收購案，由董事會授權董事長代表本公司處理與本公開收\r\n購案有關之一切必要程序並採取相關必要之行為，包括但不限於簽署及交付\r\n所有相關文件及合約，以及向相關主管機關提出申報等相關事項。如因主管\r\n機關指示或因應市場狀況、客觀環境變動或有其他正當理由等而致須修正本\r\n公開收購案相關申報文件、或延長公開收購期間或其他未盡事宜，授權董事\r\n長全權處理之。\r\n二、本公開收購案依據法令規定必須向金融監督管理委員會申報並公告，\r\n申報日預計於民國115年1月22日，\r\n公開收購開始日預計於民國115年1月23日。\r\n三、其他公開收購條件請詳公開收購說明書。\r\n公開收購說明書查詢網址：\r\na.公開資訊觀測站：https://mops.twse.com.tw/mops/#/web/t162sb02 \r\n(公開資訊觀測站//主題專區//公開收購資訊)\r\nb.元大證券股份有限公司之網頁：https://www.yuanta.com.tw\r\n註二、既存或新設公司承受消滅公司權利義務相關事項，包括庫藏股及已發行具有股權性質有\r\n　　　價證券之處理原則。\r\n註三：參與合併公司之基本資料包括公司名稱及所營業務之主要內容。\r\n註四：倘涉營運模式變更，請於欄位敘明包括營業範圍變更、產品線擴充/縮減、製程調整、產業\r\n　　　水平/垂直整合，或其他涉及營運架構調整事項。\r\n註五：非屬私募資金用以併購案件者，得填寫不適用。\r\n註六：若本案成就前，尚需經國內、外主管機關(如:投審會、公平交易委員會、反壟斷局或其他單位)核准或許可者，應予敘明相關事項。"},
{"出表日期":"1150122","發言日期":"1150121","發言時間":"191325","公司代號":"2301","公司名稱":"光寶科","主旨 ":"公告本公司發言人異動","符合條款":"第8款","事實發生日":"1150121","說明":"1.人員變動別（請輸入發言人、代理發言人、重要營運主管(如:執行長、營運長、\n行銷長及策略長等)、財務主管、會計主管、公司治理主管、資訊安全長、研發主管、\n內部稽核主管或訴訟及非訟代理人）:發言人\n2.發生變動日期:115/01/21\n3.舊任者姓名、級職及簡歷:邱森彬，本公司總經理\n4.新任者姓名、級職及簡歷:張衣宜，本公司企業品牌價值發展中心總監\n5.異動情形（請輸入「辭職」、「職務調整」、「資遣」、「退休」、「死亡」、「新\n任」或「解任」）:職務調整\n6.異動原因:職務調整\n7.生效日期:115/01/22\n8.其他應敘明事項:無"},
{"出表日期":"1150122","發言日期":"1150121","發言時間":"191859","公司代號":"6806","公司名稱":"森崴能源","主旨 ":"公告本公司董事會通過處分子公司Fox Nam及Dakpsi股權","符合條款":"第20款","事實發生日":"1140121","說明":"1.標的物之名稱及性質（屬特別股者，並應標明特別股約定發行條件，如股息率等）:\r\nFox Nam Energy Co.,Ltd之股權\nDakpsi Investment and Develop Hydroelectic Stock Company股權\r\n2.事實發生日:114/1/12~114/1/21\r\n3.董事會通過日期: 民國114年1月21日\r\n4.其他核決日期: 不適用\r\n5.交易數量、每單位價格及交易總金額:\r\nFox Nam:\n交易總金額新台幣113,400 仟元(約美金360萬元)\nDakpsi: \n交易數量:41,843,558股\n交易總金額為美金2,040萬元(約新台幣642,600仟元)\r\n6.交易相對人及其與公司之關係（交易相對人如屬自然人，且非公司之\r\n關係人者，得免揭露其姓名）:\r\n&#34886;崴能源股份有限公司，本公司持股50%之子公司\r\n7.交易相對人為關係人者，並應公告選定關係人為交易對象之原因及前次移\r\n轉之所有人、前次移轉之所有人與公司及交易相對人間相互之關係、前次\r\n移轉日期及移轉金額:\r\n選定關係人為交易對象之原因：營運規劃\n前次移轉情形:\n(1)於2024/08/23投資成立Fox Nam Energy Co.,Ltd，原始取得金額為美金350萬元。\n(2)於2024/10/30 向非關係人Mr. Vu Quang Bao 取得Dakpsi公司35%股權，\n取得金額為USD20,080,416。\r\n8.交易標的最近五年內所有權人曾為公司之關係人者，尚應公告關係人之取\r\n得及處分日期、價格及交易當時與公司之關係:\r\n不適用\r\n9.本次係處分債權之相關事項（含處分之債權附隨擔保品種類、處分債權\r\n如有屬對關係人債權者尚需公告關係人名稱及本次處分該關係人之債權\r\n帳面金額:\r\n不適用\r\n10.處分利益（或損失）（取得有價證券者不適用）（原遞延者應列表說明\r\n認列情形）:\r\n不適用\r\n11.交付或付款條件（含付款期間及金額）、契約限制條款及其他重要約定\r\n事項:\r\n依合約條件辦理。\r\n12.本次交易之決定方式、價格決定之參考依據及決策單位:\r\n價格決定之參考依據：會計師合理性意見書\n決策單位：經由本公司董事會決議通過\r\n13.取得或處分有價證券標的公司每股淨值:\r\n12.77元\r\n14.迄目前為止，累積持有本交易證券（含本次交易）之數量、金額、持股\r\n比例及權利受限情形（如質押情形）:\r\n無\r\n15.迄目前為止，依「公開發行公司取得或處分資產處理準則」第三條所列\r\n之有價證券投資（含本次交易）占公司最近期財務報表中總資產及歸屬\r\n於母公司業主之權益之比例暨最近期財務報表中營運資金數額（註二）:\r\n有價證券投資（含本次交易）占最近期財務報表中總資產之比例：43.77%\n有價證券投資（含本次交易）占最近期財務報表中股東權益之比例：123.68%\n營運資金：新台幣246,819仟元\r\n16.經紀人及經紀費用:\r\n不適用\r\n17.取得或處分之具體目的或用途:\r\n為因應公司整體資源配置及充實營運資金\r\n18.本次交易表示異議董事之意見:\r\n無\r\n19.本次交易為關係人交易:是\r\n20.監察人承認或審計委員會同意日期:\r\n114.01.12及114.01.21\r\n21.本次交易會計師出具非合理性意見:否\r\n22.會計師事務所名稱:\r\n不適用\r\n23.會計師姓名:\r\n不適用\r\n24.會計師開業證書字號:\r\n不適用\r\n25.是否涉及營運模式變更:否\r\n26.營運模式變更說明:\r\n不適用\r\n27.過去一年及預計未來一年內與交易相對人交易情形:\r\n不適用\r\n28.資金來源:\r\n不適用\r\n29.前已就同一件事件發布重大訊息日期: 不適用\r\n30.其他敘明事項:\r\n(1)本案係合併主體交易，故不認列預計處分損益。\n(2)本公司於115.1.12董事會通過處分Fox Nam股權\n本公司於115.1.21董事會通過處分Dakpsi股權\n(3)取得或處分有價證券標的公司每股淨值:\nFox Nam :不適用\nDakpsi:新台幣12.77元"},
{"出表日期":"1150122","發言日期":"1150121","發言時間":"191912","公司代號":"6806","公司名稱":"森崴能源","主旨 ":"代子公司&#34886;崴能源公告董事會通過取得Fox Nam股權及Dakpsi股權","符合條款":"第20款","事實發生日":"1140121","說明":"1.標的物之名稱及性質（屬特別股者，並應標明特別股約定發行條件，如股息率等）:\r\nFox Nam Energy Co.,Ltd之股權\nDakpsi Investment and Develop Hydroelectic Stock Company股權\r\n2.事實發生日:114/1/21~114/1/21\r\n3.董事會通過日期: 民國114年1月21日\r\n4.其他核決日期: 不適用\r\n5.交易數量、每單位價格及交易總金額:\r\nFox Nam:交易總金額新台幣113,400 仟元(約美金360萬元)\nDakpsi: \n交易數量:14,645,245股\n交易總金額為美金2,040萬元(約新台幣642,600仟元)\r\n6.交易相對人及其與公司之關係（交易相對人如屬自然人，且非公司之\r\n關係人者，得免揭露其姓名）:\r\n森崴能源股份有限公司，&#34886;崴能源為其持股50%之子公司\r\n7.交易相對人為關係人者，並應公告選定關係人為交易對象之原因及前次移\r\n轉之所有人、前次移轉之所有人與公司及交易相對人間相互之關係、前次\r\n移轉日期及移轉金額:\r\n選定關係人為交易對象之原因：營運規劃\n前次移轉情形:\n於2024/08/23投資成立Fox Nam Energy Co.,Ltd，原始取得金額為美金350萬元。\n於2024/10/30 向非關係人Mr. Vu Quang Bao 取得Dakpsi公司35%股權，\n取得金額為USD20,080,416\r\n8.交易標的最近五年內所有權人曾為公司之關係人者，尚應公告關係人之取\r\n得及處分日期、價格及交易當時與公司之關係:\r\n不適用\r\n9.本次係處分債權之相關事項（含處分之債權附隨擔保品種類、處分債權\r\n如有屬對關係人債權者尚需公告關係人名稱及本次處分該關係人之債權\r\n帳面金額:\r\n不適用\r\n10.處分利益（或損失）（取得有價證券者不適用）（原遞延者應列表說明\r\n認列情形）:\r\n不適用\r\n11.交付或付款條件（含付款期間及金額）、契約限制條款及其他重要約定\r\n事項:\r\n依合約條件辦理\r\n12.本次交易之決定方式、價格決定之參考依據及決策單位:\r\n價格決定之參考依據：會計師合理性意見書\n決策單位：經由&#34886;崴能源董事會決議通過\r\n13.取得或處分有價證券標的公司每股淨值:\r\n12.77元\r\n14.迄目前為止，累積持有本交易證券（含本次交易）之數量、金額、持股\r\n比例及權利受限情形（如質押情形）:\r\n累積持有本交易證券（含本次交易）之數量、金額、持股比例:\nFox Nam:新台幣113,400 仟元(約美金360萬元)、持股比例100%\nDakpsi: \n數量:14,645,245股\n金額為美金2,040萬元(約新台幣642,600仟元) 、持股比例35%\n權利受限情形:無\r\n15.迄目前為止，依「公開發行公司取得或處分資產處理準則」第三條所列\r\n之有價證券投資（含本次交易）占公司最近期財務報表中總資產及歸屬\r\n於母公司業主之權益之比例暨最近期財務報表中營運資金數額（註二）:\r\n有價證券投資（含本次交易）占最近期財務報表中總資產之比例：9.09%\n有價證券投資（含本次交易）占最近期財務報表中股東權益之比例：26.18%\n營運資金：新台幣246,819仟元\r\n16.經紀人及經紀費用:\r\n無\r\n17.取得或處分之具體目的或用途:\r\n為因應公司整體資源配置及充實營運資金\r\n18.本次交易表示異議董事之意見:\r\n無\r\n19.本次交易為關係人交易:是\r\n20.監察人承認或審計委員會同意日期:\r\n114.1.21\r\n21.本次交易會計師出具非合理性意見:否\r\n22.會計師事務所名稱:\r\n不適用\r\n23.會計師姓名:\r\n不適用\r\n24.會計師開業證書字號:\r\n不適用\r\n25.是否涉及營運模式變更:否\r\n26.營運模式變更說明:\r\n不適用\r\n27.過去一年及預計未來一年內與交易相對人交易情形:\r\n不適用\r\n28.資金來源:\r\n自有資金\r\n29.前已就同一件事件發布重大訊息日期: 不適用\r\n30.其他敘明事項:\r\n取得或處分有價證券標的公司每股淨值:\nFox Nam :不適用\nDakpsi:新台幣12.77元"},
{"出表日期":"1150122","發言日期":"1150121","發言時間":"192250","公司代號":"2330","公司名稱":"台積電","主旨 ":"本公司代子公司 TSMC Global Ltd. 公告取得固定收益證券","符合條款":"第20款","事實發生日":"1150121","說明":"1.證券名稱:\r\n公司債。\r\n2.交易日期:114/10/31~115/1/21\r\n3.董事會通過日期: 不適用\r\n4.其他核決日期:\r\n核決層級:不適用\r\n民國115年01月21日\r\n5.交易數量、每單位價格及交易總金額:\r\n61747YER2：225,000 單位；每單位US$100.12；總金額US$22.5 佰萬元。\r\n05583JAK8：176,270 單位；每單位US$98.27；總金額US$17.3 佰萬元。\r\n38141GZK3：150,000 單位；每單位US$98.47；總金額US$14.8 佰萬元。\r\n06738EBU8：121,350 單位；每單位US$98.15；總金額US$11.9 佰萬元。\r\n06051GKJ7：118,000 單位；每單位US$98.45；總金額US$11.6 佰萬元。\r\n74977RDL5：117,500 單位；每單位US$97.97；總金額US$11.5 佰萬元。\r\n853254CG3：115,000 單位；每單位US$98.22；總金額US$11.3 佰萬元。\r\n61747YFK6：100,000 單位；每單位US$102.56；總金額US$10.3 佰萬元。\r\n38141GWL4：100,000 單位；每單位US$99.44；總金額US$9.9 佰萬元。\r\n6.處分利益（或損失）（取得有價證券者不適用）:\r\n不適用。\r\n7.與交易標的公司之關係:\r\n無。\r\n8.迄目前為止，累積持有本交易證券（含本次交易）之數量、金額、持股\r\n比例及權利受限情形（如質押情形）:\r\n61747YER2：831,000 單位；US$82.3 佰萬元；持股比例：不適用；受限情形：無。\r\n05583JAK8：311,270 單位；US$30.6 佰萬元；持股比例：不適用；受限情形：無。\r\n38141GZK3：2,905,700 單位；US$285.3 佰萬元；持股比例：不適用；受限情形：無。\r\n06738EBU8：170,750 單位；US$16.8 佰萬元；持股比例：不適用；受限情形：無。\r\n06051GKJ7：1,212,200 單位；US$118.7 佰萬元；持股比例：不適用；受限情形：無。\r\n74977RDL5：217,500 單位；US$21.3 佰萬元；持股比例：不適用；受限情形：無。\r\n853254CG3：297,590 單位；US$29.3 佰萬元；持股比例：不適用；受限情形：無。\r\n61747YFK6：230,000 單位；US$23.5 佰萬元；持股比例：不適用；受限情形：無。\r\n38141GWL4：400,000 單位；US$39.8 佰萬元；持股比例：不適用；受限情形：無。\r\n9.迄目前為止，依「公開發行公司取得或處分資產處理準則」第三條所列之有價證券投\r\n資（含本次交易）占公司最近期財務報表中總資產及歸屬於母公司業主之權益之比例\r\n暨最近期財務報表中營運資金數額:\r\n6.87%；8.30%；NT$436,219 佰萬元。\r\n10.取得或處分之具體目的:\r\n固定收益投資。\r\n11.本次交易表示異議董事之意見:\r\n不適用\r\n12.本次交易為關係人交易:\r\n否\r\n13.交易相對人及其與公司之關係:\r\n不適用\r\n14.監察人承認或審計委員會同意日期:\r\n不適用\r\n15.前已就同一件事件發布重大訊息日期: 不適用\r\n16.其他敘明事項:\r\n無。"},
{"出表日期":"1150122","發言日期":"1150121","發言時間":"192533","公司代號":"1563","公司名稱":"巧新","主旨 ":"公告本公司取得不動產","符合條款":"第20款","事實發生日":"1150121","說明":"1.標的物之名稱及性質（如坐落台中市北區ＸＸ段ＸＸ小段土地）:\r\n土地-嘉義縣大林鎮大工一段地號240~243、245~246、262~263、265、247\n建物-嘉義縣大林鎮大埔美園區20路22號及28號全棟\r\n2.事實發生日:115/1/21~115/1/21\r\n3.董事會通過日期: 民國115年1月20日\r\n4.其他核決日期: 不適用\r\n5.交易單位數量（如ＸＸ平方公尺，折合ＸＸ坪）、每單位價格及交易總金額:\r\n土地面積：64265.82平方公尺、建物面積：17712.62平方公尺，\n交易總金額:新台幣1,230,000,000元\r\n6.交易相對人及其與公司之關係（交易相對人如屬自然人，且非公司之關\r\n係人者，得免揭露其姓名）:\r\n嘉義地方法院/無\r\n7.交易相對人為關係人者，並應公告選定關係人為交易對象之原因及前次移轉之\r\n所有人、前次移轉之所有人與公司及交易相對人間相互之關係、前次移轉日期\r\n及移轉金額:\r\n不適用\r\n8.交易標的最近五年內所有權人曾為公司之關係人者，尚應公告關係\r\n人之取得及處分日期、價格及交易當時與公司之關係:\r\n不適用\r\n9.預計處分利益（或損失）（取得資產者不適用）（遞延者應列表說明\r\n認列情形）:\r\n不適用\r\n10.交付或付款條件（含付款期間及金額）、契約限制條款及其他重要約定\r\n事項:\r\n01/21當天支付底標20%保證金，\n得標後七日內保證金抵付後付餘款。\r\n11.本次交易之決定方式（如招標、比價或議價）、價格決定之參考依據及\r\n決策單位:\r\n交易決定方式：法院拍賣\n價格決定之參考依據：法院拍賣最低總價加價15%為上限\n決策單位：董事會\r\n12.專業估價者事務所或公司名稱及其估價金額:\r\n不適用\r\n13.專業估價師姓名:\r\n不適用\r\n14.專業估價師開業證書字號:\r\n不適用\r\n15.估價報告是否為限定價格、特定價格或特殊價格:否或不適用\r\n16.是否尚未取得估價報告:否或不適用\r\n17.尚未取得估價報告之原因:\r\n不適用\r\n18.估價結果有重大差異時，其差異原因及會計師意見:\r\n不適用\r\n19.會計師事務所名稱:\r\n不適用\r\n20.會計師姓名:\r\n不適用\r\n21.會計師開業證書字號:\r\n不適用\r\n22.經紀人及經紀費用:\r\n不適用\r\n23.取得或處分之具體目的或用途:\r\n因應營運需求\r\n24.本次交易表示異議之董事之意見:\r\n無\r\n25.本次交易為關係人交易:否\r\n26.監察人承認或審計委員會同意日期:\r\n1.民國115年01月20日\n2.不適用，請寫原因\n(以上文字請自行增刪)\r\n27.本次交易係向關係人取得不動產或其使用權資產:否\r\n28.依「公開發行公司取得或處分資產處理準則」第十六條規定\r\n評估之價格:不適用\r\n29.依前項評估之價格較交易價格為低者，依同準則第十七條規\r\n定評估之價格:不適用\r\n30.前已就同一件事件發布重大訊息日期: 不適用\r\n31.其他敘明事項:\r\n無"},
{"出表日期":"1150122","發言日期":"1150121","發言時間":"200005","公司代號":"2062","公司名稱":"橋椿","主旨 ":"公告本公司董事會通過和關係人簽訂租賃契約。","符合條款":"第20款","事實發生日":"1150121","說明":"1.標的物之名稱及性質（如坐落台中市北區ＸＸ段ＸＸ小段土地）:\r\n彰化縣鹿港鎮振興段地號984、984-1、986、987、988、989-1、992、\n993、994、995等土地及其地上建物A、B、D棟。\r\n2.事實發生日:115/1/21~115/1/21\r\n3.董事會通過日期: 民國115年1月21日\r\n4.其他核決日期: 不適用\r\n5.交易單位數量（如ＸＸ平方公尺，折合ＸＸ坪）、每單位價格及交易總金額:\r\n租賃面積：廠房5,205.15坪、土地4,207.71坪\n每月租金：NT$ 2,860,000\r\n6.交易相對人及其與公司之關係（交易相對人如屬自然人，且非公司之關\r\n係人者，得免揭露其姓名）:\r\n交易相對人：楊正發、楊慶祺、楊麗玉、楊桂鳳、楊淑絹、楊淑暉\n           (以上為黃碧華(下稱黃女士)遺產分割前之共同繼承人)\n與公司之關係：(1)楊正發、楊慶祺、楊淑絹為本公司董事\n             (2)黃碧華、楊麗玉、楊桂鳳、楊淑暉為本公司董事之二親等以內親屬\r\n7.交易相對人為關係人者，並應公告選定關係人為交易對象之原因及前次移轉之\r\n所有人、前次移轉之所有人與公司及交易相對人間相互之關係、前次移轉日期\r\n及移轉金額:\r\n1.選定關係人為交易對象之原因:\n本租賃標的物A棟為公司目前承租之物流倉庫，若再增加承租B、D棟，可整合倉儲管理\n功能，降低倉儲營運管理，若尋求其他倉庫，則會使倉儲地點分散，因此，仍選定與該\n關係人承租。\n2.前次移轉資訊：\n土地：除下列所述外，黃女士於民國81年8月5日前向非關係人取得\n土地及建物：建物8,004.7平方公尺(2,421.44坪)及土地3,095平方公尺(936.2375坪)\n          (地號984、986、987、989-1)於民國106年12月5日經本公司董事會通過，\n          以交易金額NT$ 72,090,287出售予黃女士，其為本公司董事之二親等以內親屬。\r\n8.交易標的最近五年內所有權人曾為公司之關係人者，尚應公告關係\r\n人之取得及處分日期、價格及交易當時與公司之關係:\r\n一、A棟\n(一)關係人原取得日期：民國107年3月2日\n(二)關係人原取得價格：NT$ 72,090,287\n(三)交易對象及其與公司和關係人之關係：交易對象為本公司；黃女士為本公司\n    董事之二親等以內親屬。\n(四)本公司於民國107年3月2日出售予黃女士，出售面積為土地3,095平方公尺\n    (936.24坪)、建物8,004.7平方公尺(2,421.44坪)。\n二、B、D棟\n(一)關係人原取得日期：\n    土地：於民國81年8月5日前向非關係人取得(面積3,191.65坪)\n    廠房：自民國113年4月2日取得建照後開始興建(面積4,189.09坪)\n(二)關係人原取得價格：\n    1.未計入土地：\n      土地係於民國81年8月5日前持有，因無法取得原取得成本資訊，\n      故未能依「公開發行公司取得或處分資產處理準則」第16條規定計入。\n      B、D棟廠房加計上述於民國107年3月2日之取得價格後，關係人原取得\n      價格約NT$ 410,208,283。\n    2.計入土地：\n      若土地原取得成本以近期第三方估價金額替代，加計B、D棟廠房及上述\n      於民國107年3月2日取得價格後，則關係人原取得價格約為NT$ 900,928,783。\n(三)交易對象及其與公司和關係人之關係：\n     本租賃標的物之舊廠房原係本公司出售予黃女士，其為本公司董事之二親等以內親屬，\n     後其委託非關係人拆除該舊廠房並興建廠房。\r\n9.預計處分利益（或損失）（取得資產者不適用）（遞延者應列表說明\r\n認列情形）:\r\n不適用\r\n10.交付或付款條件（含付款期間及金額）、契約限制條款及其他重要約定\r\n事項:\r\n交付或付款條件：依租賃契約書約定。\n契約限制條款：無。\n其他重要約定事項：無。\r\n11.本次交易之決定方式（如招標、比價或議價）、價格決定之參考依據及\r\n決策單位:\r\n1.交易決定方式：議價\n2.價格決定之參考依據:參考市場行情。\n3.決策單位: 本公司之董事會。\r\n12.專業估價者事務所或公司名稱及其估價金額:\r\n不適用\r\n13.專業估價師姓名:\r\n不適用\r\n14.專業估價師開業證書字號:\r\n不適用\r\n15.估價報告是否為限定價格、特定價格或特殊價格:否或不適用\r\n16.是否尚未取得估價報告:否或不適用\r\n17.尚未取得估價報告之原因:\r\n不適用\r\n18.估價結果有重大差異時，其差異原因及會計師意見:\r\n不適用\r\n19.會計師事務所名稱:\r\n不適用\r\n20.會計師姓名:\r\n不適用\r\n21.會計師開業證書字號:\r\n不適用\r\n22.經紀人及經紀費用:\r\n不適用\r\n23.取得或處分之具體目的或用途:\r\n本公司增加承租相鄰的新建廠房，並併入烏日倉物料倉儲功能，可提升倉\n儲管理效率，故向關係人承租此租賃標的有其必要性。\r\n24.本次交易表示異議之董事之意見:\r\n無\r\n25.本次交易為關係人交易:是\r\n26.監察人承認或審計委員會同意日期:\r\n1.民國 115 年 1 月 21 日\r\n27.本次交易係向關係人取得不動產或其使用權資產:是\r\n28.依「公開發行公司取得或處分資產處理準則」第十六條規定\r\n評估之價格:410,208,283元\r\n29.依前項評估之價格較交易價格為低者，依同準則第十七條規\r\n定評估之價格:不適用\r\n30.前已就同一件事件發布重大訊息日期: 不適用\r\n31.其他敘明事項:\r\n本公司目前已向關係人承租標的物A棟，現因營運需求，擬再向關係人增加承租B、D棟，\n原A棟租約將協議提前終止後併入新租約。"},
{"出表日期":"1150122","發言日期":"1150121","發言時間":"210743","公司代號":"2460","公司名稱":"建通","主旨 ":"代重要子公司東莞建通電子五金有限公司\r\n依「公開發行公司資金貸與及背書保證處理準則」\r\n第二十二條第一項第三款規定公告。","符合條款":"第23款","事實發生日":"1150121","說明":"1.事實發生日:115/01/21\r\n2.接受資金貸與之:\r\n(1)公司名稱:蘇州建通光電端子有限公司\r\n(2)與資金貸與他人公司之關係:\r\n本公司之聯屬公司\r\n(3)資金貸與之限額(仟元):136,407\r\n(4)原資金貸與之餘額(仟元):67,478\r\n(5)本次新增資金貸與之金額(仟元):67,478\r\n(6)是否為董事會授權董事長對同一貸與對象分次撥貸或循環動用之資金貸與:否\r\n(7)迄事實發生日止資金貸與餘額(仟元):134,956\r\n(8)本次新增資金貸與之原因:\r\n營運發展所需。\r\n3.接受資金貸與公司所提供擔保品之:\r\n(1)內容:\r\n無。\r\n(2)價值(仟元):0\r\n4.接受資金貸與公司最近期財務報表之:\r\n(1)資本(仟元):1,127,678\r\n(2)累積盈虧金額(仟元):-112,975\r\n5.計息方式:\r\n借款到期利息一次付清。\r\n6.還款之:\r\n(1)條件:\r\n資金貸放自第一次放款日起以二個月為限。\r\n(2)日期:\r\n視資金狀況而定。\r\n7.迄事實發生日為止，資金貸與餘額(仟元):\r\n134,956\r\n8.迄事實發生日為止，資金貸與餘額占公開發行公司最近期財務報表淨值之比率:\r\n9.11\r\n9.公司貸與他人資金之來源:\r\n子公司本身\r\n10.其他應敘明事項:\r\n無。"},
{"出表日期":"1150122","發言日期":"1150121","發言時間":"222147","公司代號":"1101","公司名稱":"台泥","主旨 ":"本公司及代子公司信昌投資公告一年內累積處分有價證券\r\n達新台幣三億元","符合條款":"第20款","事實發生日":"1150121","說明":"1.證券名稱:\r\n飛宏科技股份有限公司(2457飛宏)\r\n中國海螺創業控股有限公司(00586海螺創業.HK)\r\n2.交易日期:115/1/12~115/1/21\r\n3.董事會通過日期: 不適用\r\n4.其他核決日期:\r\n核決層級:董事會授權董事長核決\r\n民國115年1月21日\r\n5.交易數量、每單位價格及交易總金額:\r\n(1)臺灣水泥股份有限公司(以下稱台泥)處分飛宏\r\n　交易數量:19,646,905股；每股平均價格約新台幣34.27元；\r\n　交易總金額:約新台幣6.73億元\r\n(2)信昌投資股份有限公司(以下稱信昌投資)處分海螺創業\r\n　交易數量:8,494,500股；每股平均價格:約港幣9.59元   \r\n　交易總金額:約港幣81,505仟元\r\n6.處分利益（或損失）（取得有價證券者不適用）:\r\n本次處分為出售透過其他綜合損益按公允價值衡量之金融資產，\r\n處分結果將計入資產負債表之權益項下，並不影響本公司當期損益\r\n7.與交易標的公司之關係:\r\n非關係人\r\n8.迄目前為止，累積持有本交易證券（含本次交易）之數量、金額、持股\r\n比例及權利受限情形（如質押情形）:\r\n(1)台泥持有飛宏\r\n累積持有數量、金額、持股比例：0\r\n權利受限情形：無\r\n(2)信昌投資持有海螺創業\r\n累積持有數量：2,615.5仟股\r\n累積投資金額：港幣25,575仟元\r\n累積持股比例：不適用\r\n權利受限情形：無\r\n9.迄目前為止，依「公開發行公司取得或處分資產處理準則」第三條所列之有價證券投\r\n資（含本次交易）占公司最近期財務報表中總資產及歸屬於母公司業主之權益之比例\r\n暨最近期財務報表中營運資金數額:\r\n占公司最近期財務報表中總資產比例：84.59%\r\n占公司最近期財務報表中歸屬於母公司業主之權益之比例：151.97%\r\n最近期財務報表中營運資金數額：新台幣(6,368,469)仟元\r\n10.取得或處分之具體目的:\r\n資金規劃\r\n11.本次交易表示異議董事之意見:\r\n不適用\r\n12.本次交易為關係人交易:\r\n否\r\n13.交易相對人及其與公司之關係:\r\n無\r\n14.監察人承認或審計委員會同意日期:\r\n不適用\r\n15.前已就同一件事件發布重大訊息日期: 不適用\r\n16.其他敘明事項:\r\n無"},
{"出表日期":"1150122","發言日期":"1150121","發言時間":"225124","公司代號":"2352","公司名稱":"佳世達","主旨 ":"代重要子公司佳世達納閩馬來西亞股份有限公司\r\n公告董事會決議股利分派","符合條款":"第14款","事實發生日":"1150121","說明":"1.董事會決議日期:115/01/21\n2.發放股利種類及金額:現金股利美金5,807,358.22\n3.其他應敘明事項:無。"}]
